{"licenses": [{"name": "", "id": 0, "url": ""}], "info": {"contributor": "", "date_created": "", "description": "", "url": "", "version": "", "year": ""}, "categories": [{"id": 1, "name": "window pane", "supercategory": ""}, {"id": 2, "name": "window frame", "supercategory": ""}, {"id": 3, "name": "open-window", "supercategory": ""}, {"id": 4, "name": "wall frame", "supercategory": ""}, {"id": 5, "name": "wall", "supercategory": ""}, {"id": 6, "name": "shutter", "supercategory": ""}, {"id": 7, "name": "blind", "supercategory": ""}, {"id": 8, "name": "bars", "supercategory": ""}, {"id": 9, "name": "misc object", "supercategory": ""}, {"id": 10, "name": "balcony", "supercategory": ""}, {"id": 11, "name": "door", "supercategory": ""}], "images": [{"id": 1, "width": 2689, "height": 2602, "file_name": "dee22d2d609edb08c2340898a9021dc5.jpg", "license": 0, "flickr_url": "", "coco_url": "", "date_captured": 0}, {"id": 2, "width": 4429, "height": 3774, "file_name": "dedca84f18e05f5e9f2dfc9070c7fe6e.jpg", "license": 0, "flickr_url": "", "coco_url": "", "date_captured": 0}, {"id": 3, "width": 4000, "height": 6000, "file_name": "deaa6cd763ede56285619e4a005a5fbb.jpg", "license": 0, "flickr_url": "", "coco_url": "", "date_captured": 0}, {"id": 4, "width": 4000, "height": 6000, "file_name": "dea502a26b62625a5fcda41e917cd249.jpg", "license": 0, "flickr_url": "", "coco_url": "", "date_captured": 0}, {"id": 5, "width": 3334, "height": 5262, "file_name": "de2618f01a3f68f2863358c606ebbaa1.jpg", "license": 0, "flickr_url": "", "coco_url": "", "date_captured": 0}], "annotations": [{"id": 1, "image_id": 1, "category_id": 1, "segmentation": [[1071.3, 1250.4, 1317.48, 1250.39, 1316.34, 1575.02, 1070.17, 1575.02]], "area": 79998.0, "bbox": [1070.17, 1250.39, 247.31, 324.63], "iscrowd": 0, "attributes": {"occluded": false}}, {"id": 2, "image_id": 1, "category_id": 4, "segmentation": [[1007.2, 421.2, 963.45, 294.18, 1116.95, 296.22, 1509.92, 297.59, 1954.74, 298.27, 1944.8, 423.9, 1777.0, 416.8, 1596.2, 412.4, 1426.1, 415.7, 1251.5, 416.4, 1110.7, 416.4, 1051.2, 417.9]], "area": 115153.0, "bbox": [963.45, 294.18, 991.29, 129.72], "iscrowd": 0, "attributes": {"wall frame": false, "window apron": false, "window header": true, "occluded": false}}, {"id": 3, "image_id": 1, "category_id": 4, "segmentation": [[1938.82, 2070.69, 1900.84, 2019.09, 1916.19, 455.64, 1034.4, 448.82, 1027.4, 2015.3, 1012.97, 2070.69, 1004.64, 1997.12, 999.09, 1479.37, 1007.2, 421.2, 1051.2, 417.9, 1110.7, 416.4, 1251.5, 416.4, 1426.1, 415.7, 1596.2, 412.4, 1777.0, 416.8, 1944.8, 423.9, 1940.21, 972.72, 1938.82, 1913.84]], "area": 129288.0, "bbox": [999.09, 412.4, 945.71, 1658.29], "iscrowd": 0, "attributes": {"wall frame": true, "window apron": false, "window header": false, "occluded": false}}, {"id": 4, "image_id": 1, "category_id": 4, "segmentation": [[1011.9, 2074.1, 961.2, 2085.3, 958.97, 2167.12, 980.3, 2176.1, 1968.38, 2171.61, 1966.14, 2076.28, 1938.82, 2070.69, 1900.84, 2019.09, 1027.4, 2015.3]], "area": 151455.0, "bbox": [958.97, 2015.3, 1009.41, 160.8], "iscrowd": 0, "attributes": {"wall frame": false, "window apron": true, "window header": false, "occluded": false}}, {"id": 5, "image_id": 1, "category_id": 1, "segmentation": [[1352.5, 867.9, 1596.1, 868.8, 1595.8, 1207.8, 1351.1, 1208.8]], "area": 82990.0, "bbox": [1351.1, 867.9, 245.0, 340.9], "iscrowd": 0, "attributes": {"occluded": false}}, {"id": 6, "image_id": 1, "category_id": 5, "segmentation": [[2689.0, 0.0, 2651.26, 0.0, 2660.56, 2602.0, 2689.0, 2602.0]], "area": 86142.0, "bbox": [2651.26, 0.0, 37.74, 2602.0], "iscrowd": 0, "attributes": {"occluded": false}}, {"id": 7, "image_id": 1, "category_id": 5, "segmentation": [[2307.54, 197.88, 2539.71, 63.29, 2546.44, 1428.24, 2550.92, 2602.0, 2227.91, 2602.0, 2227.91, 2388.3, 2268.29, 2386.05, 2259.32, 2358.02, 2226.79, 2366.99, 2227.91, 1500.02, 2236.89, 896.61, 2280.63, 889.88, 2279.51, 865.21, 2233.52, 864.09, 2246.98, 440.14, 2295.21, 437.89, 2295.21, 406.49, 2251.47, 406.49, 2251.47, 321.25, 2285.11, 322.37, 2280.63, 224.8]], "area": 759146.0, "bbox": [2226.79, 63.29, 324.13, 2538.71], "iscrowd": 0, "attributes": {"occluded": false}}, {"id": 8, "image_id": 1, "category_id": 1, "segmentation": [[1345.2, 1600.9, 1593.53, 1600.9, 1594.22, 1937.92, 1344.52, 1941.34]], "area": 84330.0, "bbox": [1344.52, 1600.9, 249.7, 340.44], "iscrowd": 0, "attributes": {"occluded": false}}, {"id": 9, "image_id": 1, "category_id": 2, "segmentation": [[1027.4, 2015.3, 1900.84, 2019.09, 1916.19, 455.64, 1034.4, 448.9, 1075.03, 503.27, 1318.67, 503.27, 1319.66, 678.14, 1318.67, 839.25, 1351.29, 838.86, 1349.92, 505.72, 1597.48, 505.72, 1597.48, 837.88, 1628.87, 838.06, 1629.5, 506.8, 1874.99, 506.14, 1875.19, 839.05, 1873.88, 867.96, 1874.7, 1204.1, 1627.37, 1206.0, 1595.8, 1207.8, 1351.1, 1208.8, 1318.85, 1204.77, 1070.74, 1203.44, 1071.3, 1250.4, 1317.48, 1250.39, 1346.6, 1252.5, 1595.6, 1251.36, 1624.6, 1253.1, 1873.04, 1250.79, 1873.61, 1578.83, 1872.9, 1606.4, 1871.88, 1942.7, 1623.6, 1941.3, 1622.8, 1602.4, 1593.53, 1600.9, 1594.22, 1937.92, 1344.52, 1941.34, 1345.2, 1600.9, 1315.18, 1602.95, 1315.86, 1939.97, 1071.0, 1938.6, 1069.58, 1600.22, 1070.17, 1575.02, 1071.36, 1251.01, 1070.22, 1203.25, 1072.68, 867.35, 1072.09, 841.22, 1074.9, 503.3, 1034.4, 448.82]], "area": 299542.0, "bbox": [1027.4, 448.82, 888.79, 1570.27], "iscrowd": 0, "attributes": {"occluded": false}}, {"id": 10, "image_id": 1, "category_id": 1, "segmentation": [[1072.68, 867.35, 1310.04, 869.71, 1318.57, 877.77, 1318.85, 1204.77, 1070.74, 1203.44]], "area": 82938.0, "bbox": [1070.74, 867.35, 248.11, 337.42], "iscrowd": 0, "attributes": {"occluded": false}}, {"id": 11, "image_id": 1, "category_id": 1, "segmentation": [[1349.92, 505.72, 1597.48, 505.72, 1597.48, 837.88, 1351.29, 838.86]], "area": 81884.0, "bbox": [1349.92, 505.72, 247.56, 333.14], "iscrowd": 0, "attributes": {"occluded": false}}, {"id": 12, "image_id": 1, "category_id": 1, "segmentation": [[1075.03, 503.27, 1318.67, 503.27, 1319.66, 678.14, 1318.67, 839.25, 1199.8, 840.2, 1072.09, 841.22]], "area": 82818.0, "bbox": [1072.09, 503.27, 247.57, 337.95], "iscrowd": 0, "attributes": {"occluded": false}}, {"id": 13, "image_id": 1, "category_id": 2, "segmentation": [[1069.58, 1600.22, 1070.17, 1575.02, 1316.34, 1575.02, 1317.48, 1250.39, 1346.6, 1252.5, 1345.45, 1574.28, 1595.03, 1577.13, 1595.6, 1251.36, 1624.6, 1253.1, 1622.32, 1575.42, 1873.61, 1578.83, 1872.9, 1606.4, 1622.8, 1602.4, 1593.53, 1600.9, 1345.2, 1600.9, 1315.18, 1602.95]], "area": 39786.0, "bbox": [1069.58, 1250.39, 804.03, 356.01], "iscrowd": 0, "attributes": {"occluded": false}}, {"id": 14, "image_id": 1, "category_id": 2, "segmentation": [[1072.09, 841.22, 1318.67, 839.25, 1351.29, 838.86, 1597.48, 837.88, 1628.87, 838.06, 1875.19, 839.05, 1873.88, 867.96, 1627.0, 868.0, 1627.37, 1206.0, 1595.8, 1207.8, 1596.1, 868.8, 1352.5, 867.9, 1351.1, 1208.8, 1318.85, 1204.77, 1318.57, 877.77, 1310.04, 869.71, 1072.68, 867.35]], "area": 45229.0, "bbox": [1072.09, 837.88, 803.1, 370.92], "iscrowd": 0, "attributes": {"occluded": false}}, {"id": 15, "image_id": 1, "category_id": 5, "segmentation": [[0.0, 260.69, 963.45, 294.18, 1007.2, 421.2, 999.09, 1479.37, 1004.64, 1997.12, 1012.97, 2070.69, 1011.9, 2074.1, 961.2, 2085.3, 958.97, 2167.12, 980.3, 2176.1, 1968.38, 2171.61, 1966.14, 2076.28, 1938.82, 2070.69, 1938.82, 1913.84, 1940.21, 972.72, 1944.8, 423.9, 1954.74, 298.27, 2053.4, 291.64, 2027.83, 340.09, 2038.59, 418.15, 2111.27, 348.17, 2177.22, 323.94, 2174.53, 594.46, 2105.89, 595.81, 2108.58, 620.04, 2175.87, 618.69, 2169.14, 683.29, 1979.37, 688.68, 1976.68, 711.56, 2169.14, 707.52, 2155.68, 2368.33, 2142.23, 2369.68, 2140.88, 2396.6, 2157.03, 2396.6, 2158.38, 2602.0, 0.0, 2602.0]], "area": 3222100.0, "bbox": [0.0, 260.69, 2177.22, 2341.31], "iscrowd": 0, "attributes": {"occluded": false}}, {"id": 16, "image_id": 1, "category_id": 1, "segmentation": [[1071.0, 1938.6, 1315.86, 1939.97, 1315.18, 1602.95, 1069.58, 1600.22]], "area": 82796.0, "bbox": [1069.58, 1600.22, 246.28, 339.75], "iscrowd": 0, "attributes": {"occluded": false}}, {"id": 17, "image_id": 1, "category_id": 1, "segmentation": [[1623.2, 1602.4, 1872.9, 1606.4, 1871.88, 1942.7, 1623.6, 1941.3]], "area": 84156.0, "bbox": [1623.2, 1602.4, 249.7, 340.3], "iscrowd": 0, "attributes": {"occluded": false}}, {"id": 18, "image_id": 1, "category_id": 1, "segmentation": [[1627.0, 868.0, 1873.88, 867.96, 1874.7, 1204.1, 1627.37, 1206.0]], "area": 83368.0, "bbox": [1627.0, 867.96, 247.7, 338.04], "iscrowd": 0, "attributes": {"occluded": false}}, {"id": 19, "image_id": 1, "category_id": 1, "segmentation": [[1346.6, 1252.5, 1595.6, 1251.36, 1595.03, 1577.13, 1345.45, 1574.28]], "area": 80657.0, "bbox": [1345.45, 1251.36, 250.15, 325.77], "iscrowd": 0, "attributes": {"occluded": false}}, {"id": 20, "image_id": 1, "category_id": 1, "segmentation": [[1629.5, 506.8, 1874.99, 506.14, 1875.19, 839.05, 1771.16, 839.44, 1628.87, 838.06]], "area": 81703.0, "bbox": [1628.87, 506.14, 246.32, 333.3], "iscrowd": 0, "attributes": {"occluded": false}}, {"id": 21, "image_id": 1, "category_id": 1, "segmentation": [[1624.6, 1253.1, 1873.04, 1250.79, 1873.61, 1578.83, 1622.32, 1575.42]], "area": 81170.0, "bbox": [1622.32, 1250.79, 251.29, 328.04], "iscrowd": 0, "attributes": {"occluded": false}}, {"id": 22, "image_id": 2, "category_id": 5, "segmentation": [[0.52, 624.11, 0.0, 966.44, 236.9, 948.92, 168.1, 929.45, 121.37, 883.36, 107.09, 841.82, 118.13, 817.16, 118.13, 806.77, 183.03, 806.77, 257.67, 808.72, 340.75, 804.83, 361.52, 831.44, 363.47, 860.0, 382.94, 870.38, 392.68, 896.99, 386.19, 911.27, 388.78, 927.5, 426.43, 963.85, 433.57, 1021.61, 392.68, 1074.83, 351.14, 1087.82, 493.4, 1097.7, 510.3, 659.4]], "area": 134753.0, "bbox": [0.0, 624.11, 510.3, 473.59], "iscrowd": 0, "attributes": {"occluded": false}}, {"id": 23, "image_id": 2, "category_id": 1, "segmentation": [[886.42, 753.17, 806.5, 3323.5, 3747.9, 3290.8, 3721.67, 1729.91, 3700.65, 887.76]], "area": 7162341.0, "bbox": [806.5, 753.17, 2941.4, 2570.33], "iscrowd": 0, "attributes": {"occluded": false}}, {"id": 24, "image_id": 2, "category_id": 2, "segmentation": [[808.01, 1633.61, 840.47, 680.8, 3776.79, 817.75, 3800.46, 1729.88, 3835.0, 3386.0, 3749.6, 3387.3, 3723.77, 1728.84, 3700.65, 887.76, 886.42, 753.17, 859.5, 1634.73]], "area": 454655.0, "bbox": [808.01, 680.8, 3026.99, 2706.5], "iscrowd": 0, "attributes": {"occluded": false}}, {"id": 25, "image_id": 2, "category_id": 5, "segmentation": [[0.0, 966.44, 236.9, 948.92, 283.57, 929.59, 287.6, 948.43, 278.18, 972.66, 279.53, 1022.45, 302.41, 1066.87, 332.02, 1084.36, 351.14, 1087.82, 493.4, 1097.7, 405.5, 3386.5, 400.88, 3386.49, 354.9, 3406.68, 353.78, 3465.0, 779.97, 3458.27, 2649.62, 3436.96, 4151.4, 3439.21, 4181.68, 3422.38, 4174.95, 3392.1, 4129.0, 3361.8, 4070.24, 827.49, 4109.74, 828.33, 4128.65, 811.94, 4143.35, 809.84, 4138.73, 784.63, 4126.97, 781.68, 4128.65, 770.76, 4307.66, 508.13, 4400.94, 459.38, 4383.29, 405.18, 0.0, 167.0, 0.0, 0.0, 4429.0, 0.0, 4424.84, 368.36, 4406.0, 365.66, 4391.19, 379.12, 4396.57, 432.96, 4400.61, 455.84, 4410.03, 869.02, 4429.0, 870.37, 4429.0, 3774.0, 0.0, 3774.0]], "area": 4742152.0, "bbox": [0.0, 0.0, 4429.0, 3774.0], "iscrowd": 0, "attributes": {"occluded": false}}, {"id": 26, "image_id": 2, "category_id": 2, "segmentation": [[3747.9, 3290.7, 3749.6, 3387.4, 752.4, 3393.7, 752.8, 3324.3]], "area": 248716.0, "bbox": [752.4, 3290.7, 2997.2, 103.0], "iscrowd": 0, "attributes": {"occluded": false}}, {"id": 27, "image_id": 2, "category_id": 4, "segmentation": [[0.52, 624.11, 840.47, 680.8, 3776.79, 817.75, 4070.24, 827.49, 4109.74, 828.33, 4128.65, 811.94, 4143.35, 809.84, 4138.73, 784.63, 4126.97, 781.68, 4128.65, 770.76, 4307.66, 508.13, 4400.94, 459.38, 4383.29, 405.18, 0.0, 167.0]], "area": 1936316.0, "bbox": [0.0, 167.0, 4400.94, 661.33], "iscrowd": 0, "attributes": {"wall frame": false, "window apron": false, "window header": false, "occluded": false}}, {"id": 28, "image_id": 2, "category_id": 4, "segmentation": [[840.47, 680.8, 510.2, 658.3, 405.5, 3386.5, 752.7, 3396.0, 808.01, 1633.61]], "area": 921114.0, "bbox": [405.5, 658.3, 434.97, 2737.7], "iscrowd": 0, "attributes": {"wall frame": true, "window apron": false, "window header": false, "occluded": false}}, {"id": 29, "image_id": 2, "category_id": 4, "segmentation": [[3776.79, 817.75, 3800.8, 1730.32, 3835.9, 3388.4, 4129.6, 3362.3, 4070.24, 827.49]], "area": 745896.0, "bbox": [3776.79, 817.75, 352.81, 2570.65], "iscrowd": 0, "attributes": {"wall frame": true, "window apron": false, "window header": false, "occluded": false}}, {"id": 30, "image_id": 2, "category_id": 4, "segmentation": [[400.88, 3386.49, 354.9, 3406.68, 353.78, 3465.0, 779.97, 3458.27, 2649.62, 3436.96, 4151.4, 3439.21, 4181.68, 3422.38, 4174.95, 3392.1, 4129.0, 3361.3, 3837.3, 3388.4, 3836.4, 3387.0, 3750.15, 3387.41, 660.27, 3394.76]], "area": 212891.0, "bbox": [353.78, 3361.3, 3827.9, 103.7], "iscrowd": 0, "attributes": {"wall frame": false, "window apron": true, "window header": false, "occluded": false}}, {"id": 31, "image_id": 2, "category_id": 2, "segmentation": [[807.95, 1633.57, 858.8, 1634.3, 806.71, 3323.39, 753.46, 3323.89]], "area": 88043.0, "bbox": [753.46, 1633.57, 105.34, 1690.32], "iscrowd": 0, "attributes": {"occluded": false}}, {"id": 32, "image_id": 3, "category_id": 4, "segmentation": [[2371.62, 4662.92, 2380.88, 4468.43, 2158.6, 4490.29, 908.1, 4547.6, 600.81, 4553.64, 537.83, 4570.31, 530.42, 4737.02, 605.0, 4742.0, 1135.0, 4715.1, 1795.2, 4687.8, 2314.4, 4653.1]], "area": 330604.0, "bbox": [530.42, 4468.43, 1850.46, 273.57], "iscrowd": 0, "attributes": {"wall frame": false, "window apron": true, "window header": false, "occluded": false}}, {"id": 33, "image_id": 3, "category_id": 4, "segmentation": [[2258.62, 1427.31, 2454.04, 854.9, 2119.14, 776.76, 1689.36, 762.81, 1343.3, 796.3, 1080.96, 877.23, 782.34, 997.24, 912.84, 1542.63, 1061.03, 1483.36, 1227.74, 1420.38, 1500.03, 1364.81, 1668.59, 1351.84, 1840.85, 1349.99, 2092.77, 1387.04]], "area": 900651.0, "bbox": [782.34, 762.81, 1671.7, 779.82], "iscrowd": 0, "attributes": {"wall frame": false, "window apron": false, "window header": true, "occluded": false}}, {"id": 34, "image_id": 3, "category_id": 4, "segmentation": [[2258.62, 1427.31, 2092.77, 1387.04, 1840.85, 1349.99, 1668.59, 1351.84, 1500.03, 1364.81, 1227.74, 1420.38, 1061.03, 1483.36, 912.84, 1542.63, 785.03, 4550.78, 908.1, 4547.6, 940.52, 4010.17, 978.31, 3274.43, 1011.65, 2343.09, 1044.99, 1576.23, 1247.26, 1491.77, 1456.2, 1429.53, 1671.81, 1396.19, 1847.41, 1385.07, 2007.45, 1393.97, 2180.83, 1413.97]], "area": 461400.0, "bbox": [785.03, 1349.99, 1473.59, 3200.79], "iscrowd": 0, "attributes": {"wall frame": true, "window apron": false, "window header": false, "occluded": false}}, {"id": 35, "image_id": 3, "category_id": 5, "segmentation": [[912.84, 1542.63, 647.76, 1490.23, 655.54, 1268.25, 632.18, 1263.71, 471.21, 1277.34, 462.13, 1286.43, 454.34, 1496.72, 0.0, 1552.54, 0.0, 0.0, 4000.0, 0.0, 4000.0, 4954.23, 4000.0, 4996.99, 3939.5, 4980.9, 2428.1, 5038.5, 2371.62, 4662.92, 2380.88, 4468.43, 2158.6, 4490.29, 2171.94, 4261.34, 2156.4, 4225.6, 2201.2, 2896.7, 2210.04, 2812.8, 2248.29, 1551.97, 2258.62, 1427.31, 2454.04, 854.9, 2119.14, 776.76, 1689.36, 762.81, 1343.3, 796.3, 1080.96, 877.23, 782.34, 997.24]], "area": 11150123.0, "bbox": [0.0, 0.0, 4000.0, 5038.5], "iscrowd": 0, "attributes": {"occluded": false}}, {"id": 36, "image_id": 3, "category_id": 1, "segmentation": [[1158.7, 1681.1, 1268.16, 1623.31, 1394.3, 1575.75, 1599.01, 1523.02, 1760.81, 1502.34, 1974.31, 1504.93, 2160.41, 1529.22, 2248.29, 1551.97, 2210.04, 2812.8, 1768.05, 2844.85, 1464.6, 2868.63, 1446.51, 2866.05, 1185.45, 2883.1, 1138.93, 2890.34, 1115.8, 2882.1]], "area": 1422646.0, "bbox": [1115.8, 1502.34, 1132.49, 1388.0], "iscrowd": 0, "attributes": {"occluded": false}}, {"id": 37, "image_id": 3, "category_id": 1, "segmentation": [[2156.4, 4225.6, 1138.75, 4284.44, 1124.24, 4272.7, 1105.56, 4271.93, 1167.15, 2971.76, 2201.2, 2896.7]], "area": 1374191.0, "bbox": [1105.56, 2896.7, 1095.64, 1387.74], "iscrowd": 0, "attributes": {"occluded": false}}, {"id": 38, "image_id": 3, "category_id": 5, "segmentation": [[2428.1, 5038.5, 2371.62, 4662.92, 2315.4, 4653.1, 1796.0, 4687.3, 1135.0, 4715.1, 603.3, 4739.3, 530.42, 4737.02, 537.83, 4570.31, 600.81, 4553.64, 785.03, 4550.78, 912.84, 1542.63, 647.76, 1490.23, 543.32, 1502.93, 469.3, 1509.66, 454.34, 1496.72, 0.0, 1552.54, 0.0, 5042.8]], "area": 3476098.0, "bbox": [0.0, 1490.23, 2428.1, 3552.57], "iscrowd": 0, "attributes": {"occluded": false}}, {"id": 39, "image_id": 3, "category_id": 5, "segmentation": [[3939.5, 4980.9, 4000.0, 4996.99, 4000.0, 6000.0, 0.0, 6000.0, 0.0, 5042.8, 2428.1, 5038.5, 2396.44, 5068.12, 2388.8, 5226.86, 2387.2, 5298.4, 2451.8, 5306.5, 3921.97, 5267.05, 3975.01, 5228.07, 3977.83, 5032.76]], "area": 3450632.0, "bbox": [0.0, 4980.9, 4000.0, 1019.1], "iscrowd": 0, "attributes": {"occluded": false}}, {"id": 40, "image_id": 3, "category_id": 2, "segmentation": [[2158.6, 4490.29, 908.1, 4547.6, 940.52, 4010.17, 978.31, 3274.43, 1011.65, 2343.09, 1044.99, 1576.23, 1247.26, 1491.77, 1456.2, 1429.53, 1671.81, 1396.19, 1847.41, 1385.07, 2007.45, 1393.97, 2180.83, 1413.97, 2258.62, 1427.31, 2248.29, 1551.97, 2160.41, 1529.22, 1974.31, 1504.93, 1760.81, 1502.34, 1599.01, 1523.02, 1394.3, 1575.75, 1268.16, 1623.31, 1158.7, 1681.1, 1115.8, 2882.1, 1138.93, 2890.34, 1185.45, 2883.1, 1446.51, 2866.05, 1464.6, 2868.63, 1768.05, 2844.85, 2210.04, 2812.8, 2201.2, 2896.7, 1167.15, 2971.76, 1105.56, 4271.93, 1124.24, 4272.7, 1138.75, 4284.44, 2156.4, 4225.6, 2171.94, 4261.34]], "area": 953987.0, "bbox": [908.1, 1385.07, 1350.52, 3162.53], "iscrowd": 0, "attributes": {"occluded": false}}, {"id": 41, "image_id": 4, "category_id": 4, "segmentation": [[2627.1, 4183.3, 2592.02, 4234.53, 2585.56, 4263.6, 2604.94, 4287.83, 2601.71, 4375.04, 2648.55, 4450.95, 2642.09, 4539.78, 1190.15, 4279.75, 1200.96, 3919.22]], "area": 509315.0, "bbox": [1190.15, 3919.22, 1458.4, 620.56], "iscrowd": 0, "attributes": {"wall frame": false, "window apron": true, "window header": false, "occluded": false}}, {"id": 42, "image_id": 4, "category_id": 5, "segmentation": [[2075.0, 6000.0, 1190.15, 4279.75, 1200.96, 3919.22, 1208.41, 3797.85, 1257.3, 1237.2, 1260.6, 1042.77, 1246.95, 1007.7, 1270.11, 990.72, 1192.93, 444.29, 1500.1, 456.63, 1723.92, 482.87, 1918.42, 516.83, 2166.94, 577.03, 2454.04, 665.02, 2697.93, 766.9, 2809.07, 817.83, 2684.04, 1322.59, 2632.05, 1358.4, 2610.33, 1477.26, 2571.26, 4050.39, 2627.07, 4042.02, 2626.1, 4183.3, 2592.02, 4234.53, 2585.56, 4263.6, 2604.94, 4287.83, 2601.71, 4375.04, 2648.55, 4450.95, 2642.09, 4539.78, 1189.0, 4281.0, 2069.0, 5999.0, 4000.0, 4293.3, 4000.0, 0.0, 0.0, 0.0, 0.0, 6000.0]], "area": 16967744.0, "bbox": [0.0, 0.0, 4000.0, 6000.0], "iscrowd": 0, "attributes": {"occluded": false}}, {"id": 43, "image_id": 4, "category_id": 4, "segmentation": [[1257.3, 1237.2, 1260.6, 1042.77, 1458.43, 1042.77, 1560.67, 1062.77, 1707.38, 1080.55, 1791.84, 1093.89, 1925.21, 1116.12, 2063.02, 1158.35, 2214.17, 1196.14, 2307.53, 1236.15, 2445.34, 1282.83, 2547.59, 1320.61, 2632.05, 1358.4, 2610.33, 1477.26, 2571.26, 4050.39, 2627.07, 4042.02, 2626.1, 4183.3, 1200.96, 3919.22, 1208.41, 3797.85, 2447.12, 4031.51, 2479.12, 1493.28]], "area": 809889.0, "bbox": [1200.96, 1042.77, 1431.09, 3140.53], "iscrowd": 0, "attributes": {"wall frame": true, "window apron": false, "window header": false, "occluded": false}}, {"id": 44, "image_id": 4, "category_id": 1, "segmentation": [[1397.11, 1424.53, 2293.63, 1613.46, 2304.75, 1644.95, 2274.18, 3855.87, 1351.73, 3678.05]], "area": 2063050.0, "bbox": [1351.73, 1424.53, 953.02, 2431.34], "iscrowd": 0, "attributes": {"occluded": false}}, {"id": 45, "image_id": 4, "category_id": 4, "segmentation": [[1260.6, 1042.77, 1246.95, 1007.7, 1270.11, 990.72, 1192.93, 444.29, 1500.1, 456.63, 1723.92, 482.87, 1918.42, 516.83, 2166.94, 577.03, 2454.04, 665.02, 2697.93, 766.9, 2809.07, 817.83, 2684.04, 1322.59, 2632.05, 1358.4, 2547.59, 1320.61, 2445.34, 1282.83, 2307.53, 1236.15, 2214.17, 1196.14, 2063.02, 1158.35, 1925.21, 1116.12, 1791.84, 1093.89, 1707.38, 1080.55, 1560.67, 1062.77, 1458.43, 1042.77]], "area": 910506.0, "bbox": [1192.93, 444.29, 1616.14, 914.11], "iscrowd": 0, "attributes": {"wall frame": false, "window apron": false, "window header": true, "occluded": false}}, {"id": 46, "image_id": 4, "category_id": 2, "segmentation": [[1257.1, 1237.2, 1397.16, 1423.66, 2293.63, 1613.46, 2304.75, 1644.95, 2274.18, 3855.87, 1351.73, 3678.05, 1397.11, 1424.53, 1257.3, 1237.2, 1208.41, 3797.85, 2447.12, 4031.51, 2479.12, 1493.28]], "area": 1082995.0, "bbox": [1208.41, 1237.2, 1270.71, 2794.31], "iscrowd": 0, "attributes": {"occluded": false}}, {"id": 47, "image_id": 5, "category_id": 4, "segmentation": [[1094.16, 1727.21, 1098.03, 1410.74, 1077.72, 1393.14, 1064.18, 1345.76, 1022.22, 1287.55, 1023.57, 1236.11, 1007.33, 1204.97, 997.85, 1168.42, 1038.46, 1114.27, 997.85, 1102.09, 996.5, 991.08, 1070.95, 913.92, 1253.71, 813.74, 1460.83, 767.72, 1623.28, 743.35, 1839.87, 751.47, 2017.21, 816.45, 2218.92, 947.76, 2378.66, 1108.86, 2528.92, 1294.32, 2643.99, 1496.02, 2741.46, 1720.74, 2699.49, 1747.82, 2671.06, 1755.94, 2616.91, 1788.43, 2593.9, 1781.66, 2589.84, 1815.5, 2553.29, 1818.21, 2546.52, 1892.67, 2470.71, 1885.9, 2382.72, 1949.52, 2390.84, 1991.49, 2412.5, 2099.79, 2384.07, 2189.13, 2380.01, 2229.75, 1142.46, 1718.29, 1126.11, 1720.52]], "area": 1662978.0, "bbox": [996.5, 743.35, 1744.96, 1486.4], "iscrowd": 0, "attributes": {"wall frame": false, "window apron": false, "window header": true, "occluded": false}}, {"id": 48, "image_id": 5, "category_id": 4, "segmentation": [[2354.31, 4631.63, 2408.44, 4657.89, 2407.31, 4708.65, 2382.49, 4712.04, 2357.67, 4740.24, 2355.42, 4802.29, 2321.57, 4813.57, 2241.48, 4784.24, 2092.57, 4737.98, 1949.3, 4689.48, 1963.96, 4664.66, 1979.76, 4613.89, 2036.16, 4573.28, 2064.37, 4572.15, 2079.39, 4545.44, 2209.42, 4593.73, 2250.29, 4592.99]], "area": 70119.0, "bbox": [1949.3, 4545.44, 459.14, 268.13], "iscrowd": 0, "attributes": {"wall frame": false, "window apron": true, "window header": false, "occluded": false}}, {"id": 49, "image_id": 5, "category_id": 1, "segmentation": [[1241.0, 3629.9, 1251.47, 3633.16, 1240.89, 4177.83]], "area": 2790.0, "bbox": [1240.89, 3629.9, 10.58, 547.93], "iscrowd": 0, "attributes": {"occluded": false}}, {"id": 50, "image_id": 5, "category_id": 1, "segmentation": [[1542.93, 3691.33, 1700.87, 3743.97, 1705.57, 3738.33, 1707.73, 3175.78, 1553.37, 3121.63]], "area": 90669.0, "bbox": [1542.93, 3121.63, 164.8, 622.34], "iscrowd": 0, "attributes": {"occluded": false}}, {"id": 51, "image_id": 5, "category_id": 4, "segmentation": [[1235.86, 4233.03, 1126.86, 4187.31, 1146.17, 2475.42, 1084.51, 2440.5, 1094.16, 1727.21, 1126.11, 1720.52, 1142.46, 1718.29, 2418.95, 2242.86, 2410.77, 2933.85, 2370.65, 2945.74, 2362.48, 2940.54, 2354.31, 4631.63, 2250.29, 4592.99, 2209.42, 4593.73, 2079.39, 4545.44, 2074.19, 4509.03, 2002.95, 4481.48, 2007.48, 3128.65, 2001.13, 3104.16, 2015.19, 2430.47, 2002.04, 2406.44, 1253.09, 2104.95, 1251.27, 2260.91, 1260.79, 2265.9, 1253.99, 2598.67, 1248.55, 2823.53, 1247.1, 3008.7, 1240.5, 3580.3, 1240.7, 3629.98, 1251.5, 3633.43, 1240.77, 4177.8]], "area": 1461632.0, "bbox": [1084.51, 1718.29, 1334.44, 2913.34], "iscrowd": 0, "attributes": {"wall frame": true, "window apron": false, "window header": false, "occluded": false}}, {"id": 52, "image_id": 5, "category_id": 1, "segmentation": [[1290.7, 2833.6, 1445.26, 2896.38, 1446.95, 2339.76, 1292.68, 2281.56]], "area": 85717.0, "bbox": [1290.7, 2281.56, 156.25, 614.82], "iscrowd": 0, "attributes": {"occluded": false}}, {"id": 53, "image_id": 5, "category_id": 4, "segmentation": [[0.0, 284.66, 324.27, 655.74, 318.61, 690.9, 272.53, 697.37, 247.47, 738.2, 186.43, 772.15, 161.78, 775.39, 161.78, 793.58, 130.25, 791.15, 121.35, 861.08, 84.97, 861.08, 0.0, 888.16]], "area": 104469.0, "bbox": [0.0, 284.66, 324.27, 603.5], "iscrowd": 0, "attributes": {"wall frame": false, "window apron": false, "window header": true, "occluded": false}}, {"id": 54, "image_id": 5, "category_id": 1, "segmentation": [[1880.52, 3058.46, 1829.76, 3044.35, 1736.69, 3002.99, 1738.57, 2450.22, 1888.98, 2516.02, 1885.22, 3049.05]], "area": 82532.0, "bbox": [1736.69, 2450.22, 152.29, 608.24], "iscrowd": 0, "attributes": {"occluded": false}}, {"id": 55, "image_id": 5, "category_id": 1, "segmentation": [[1281.68, 3643.19, 1444.32, 3703.36, 1440.56, 4273.05, 1280.74, 4219.47]], "area": 92584.0, "bbox": [1280.74, 3643.19, 163.58, 629.86], "iscrowd": 0, "attributes": {"occluded": false}}, {"id": 56, "image_id": 5, "category_id": 5, "segmentation": [[3334.0, 966.99, 2887.28, 759.05, 2708.59, 794.79, 1315.6, 158.48, 1325.02, 133.47, 1365.8, 117.71, 1384.64, 114.62, 1381.55, 73.04, 1247.86, 11.31, 0.0, 0.0, 0.0, 284.66, 324.27, 655.74, 318.61, 690.9, 272.53, 697.37, 247.47, 738.2, 186.43, 772.15, 161.78, 775.39, 161.78, 793.58, 130.25, 791.15, 121.35, 861.08, 84.97, 861.08, 0.0, 888.16, 0.0, 4034.32, 436.11, 4174.52, 547.38, 4190.92, 974.95, 4117.82, 1126.86, 4187.31, 1146.17, 2475.42, 1084.51, 2440.5, 1094.16, 1727.21, 1098.03, 1410.74, 1077.72, 1393.14, 1064.18, 1345.76, 1022.22, 1287.55, 1023.57, 1236.11, 1007.33, 1204.97, 997.85, 1168.42, 1038.46, 1114.27, 997.85, 1102.09, 996.5, 991.08, 1070.95, 913.92, 1253.71, 813.74, 1460.83, 767.72, 1623.28, 743.35, 1839.87, 751.47, 2017.21, 816.45, 2218.92, 947.76, 2378.66, 1108.86, 2528.92, 1294.32, 2643.99, 1496.02, 2741.46, 1720.74, 2699.49, 1747.82, 2671.06, 1755.94, 2616.91, 1788.43, 2593.9, 1781.66, 2589.84, 1815.5, 2553.29, 1818.21, 2546.52, 1892.67, 2470.71, 1885.9, 2382.72, 1949.52, 2390.84, 1991.49, 2412.5, 2099.79, 2384.07, 2189.13, 2380.01, 2229.75, 2418.95, 2242.86, 2410.77, 2933.85, 2370.65, 2945.74, 2362.48, 2940.54, 2354.31, 4631.63, 2408.44, 4657.89, 2407.31, 4708.65, 2382.49, 4712.04, 2357.67, 4740.24, 2355.42, 4802.29, 2321.57, 4813.57, 2882.73, 5002.84, 3008.3, 5008.36, 3334.0, 4977.66]], "area": 8901960.0, "bbox": [0.0, 0.0, 3334.0, 5008.36], "iscrowd": 0, "attributes": {"occluded": false}}, {"id": 57, "image_id": 5, "category_id": 1, "segmentation": [[1893.02, 3809.11, 1739.6, 3757.53, 1742.21, 3187.47, 1897.33, 3244.79]], "area": 87705.0, "bbox": [1739.6, 3187.47, 157.73, 621.64], "iscrowd": 0, "attributes": {"occluded": false}}, {"id": 58, "image_id": 5, "category_id": 1, "segmentation": [[1885.7, 4416.4, 1733.71, 4370.2, 1738.41, 3798.31, 1893.53, 3853.15, 1888.83, 4284.02]], "area": 87813.0, "bbox": [1733.71, 3798.31, 159.82, 618.09], "iscrowd": 0, "attributes": {"occluded": false}}, {"id": 59, "image_id": 5, "category_id": 1, "segmentation": [[1441.97, 3656.86, 1284.63, 3600.72, 1292.21, 3031.25, 1452.02, 3086.74]], "area": 90856.0, "bbox": [1284.63, 3031.25, 167.39, 625.61], "iscrowd": 0, "attributes": {"occluded": false}}, {"id": 60, "image_id": 5, "category_id": 2, "segmentation": [[1235.86, 4233.03, 1240.89, 4177.83, 1251.47, 3633.16, 1241.0, 3629.9, 1240.5, 3580.3, 1252.7, 3585.0, 1257.4, 3014.4, 1292.21, 3031.25, 1284.63, 3600.72, 1441.97, 3656.86, 1452.02, 3086.74, 1553.37, 3121.63, 1542.93, 3691.33, 1700.87, 3743.97, 1705.57, 3738.33, 1707.73, 3175.78, 1742.21, 3187.47, 1739.6, 3757.53, 1893.02, 3809.11, 1893.53, 3853.15, 1738.41, 3798.31, 1705.51, 3790.47, 1544.13, 3731.72, 1444.32, 3703.36, 1281.68, 3643.19, 1280.74, 4219.47]], "area": 145917.0, "bbox": [1235.86, 3014.4, 657.67, 1218.63], "iscrowd": 0, "attributes": {"occluded": false}}, {"id": 61, "image_id": 5, "category_id": 1, "segmentation": [[1247.1, 3008.7, 1257.4, 3014.4, 1252.7, 3585.0, 1240.5, 3580.3]], "area": 6412.0, "bbox": [1240.5, 3008.7, 16.9, 576.3], "iscrowd": 0, "attributes": {"occluded": false}}, {"id": 62, "image_id": 5, "category_id": 1, "segmentation": [[1695.3, 2989.4, 1551.8, 2937.9, 1553.19, 2373.41, 1702.1, 2434.33]], "area": 82135.0, "bbox": [1551.8, 2373.41, 150.3, 615.99], "iscrowd": 0, "attributes": {"occluded": false}}, {"id": 63, "image_id": 5, "category_id": 2, "segmentation": [[1253.09, 2104.95, 2002.04, 2406.44, 2015.19, 2430.47, 2001.13, 3104.16, 2007.48, 3128.65, 2002.95, 4481.48, 1932.68, 4459.72, 1873.29, 4450.65, 1730.02, 4405.77, 1486.12, 4325.52, 1235.86, 4233.03, 1280.74, 4219.47, 1440.56, 4273.05, 1444.32, 3703.36, 1544.13, 3731.72, 1539.42, 4301.26, 1695.3, 4354.5, 1705.51, 3790.47, 1738.41, 3798.31, 1733.71, 4370.2, 1885.7, 4416.4, 1888.83, 4284.02, 1893.53, 3853.15, 1893.02, 3809.11, 1897.33, 3244.79, 1742.21, 3187.47, 1707.73, 3175.78, 1553.37, 3121.63, 1452.02, 3086.74, 1292.21, 3031.25, 1257.4, 3014.4, 1247.1, 3008.7, 1248.55, 2823.53, 1290.7, 2833.6, 1445.26, 2896.38, 1446.95, 2339.76, 1553.19, 2373.41, 1551.8, 2937.9, 1695.3, 2989.4, 1702.1, 2434.33, 1738.57, 2450.22, 1736.69, 3002.99, 1829.76, 3044.35, 1880.52, 3058.46, 1885.22, 3049.05, 1888.98, 2516.02, 1739.09, 2451.78, 1700.1, 2433.19, 1551.85, 2373.8, 1444.41, 2338.89, 1292.68, 2281.56, 1290.72, 2833.96, 1248.55, 2823.53, 1253.99, 2598.67, 1260.79, 2265.9, 1251.27, 2260.91]], "area": 659027.0, "bbox": [1235.86, 2104.95, 779.33, 2376.53], "iscrowd": 0, "attributes": {"occluded": false}}, {"id": 64, "image_id": 5, "category_id": 1, "segmentation": [[1539.42, 4301.26, 1695.3, 4354.5, 1705.51, 3790.47, 1544.13, 3731.72]], "area": 90364.0, "bbox": [1539.42, 3731.72, 166.09, 622.78], "iscrowd": 0, "attributes": {"occluded": false}}]}