{"licenses": [{"name": "", "id": 0, "url": ""}], "info": {"contributor": "", "date_created": "", "description": "", "url": "", "version": "", "year": ""}, "categories": [{"id": 1, "name": "window pane", "supercategory": ""}, {"id": 2, "name": "window frame", "supercategory": ""}, {"id": 3, "name": "open-window", "supercategory": ""}, {"id": 4, "name": "wall frame", "supercategory": ""}, {"id": 5, "name": "wall", "supercategory": ""}, {"id": 6, "name": "shutter", "supercategory": ""}, {"id": 7, "name": "blind", "supercategory": ""}, {"id": 8, "name": "bars", "supercategory": ""}, {"id": 9, "name": "misc object", "supercategory": ""}, {"id": 10, "name": "balcony", "supercategory": ""}, {"id": 11, "name": "door", "supercategory": ""}], "images": [{"id": 1, "width": 2899, "height": 2682, "file_name": "007fc34fa43291f55eb08ea7f70e911b.jpg", "license": 0, "flickr_url": "", "coco_url": "", "date_captured": 0}, {"id": 2, "width": 3015, "height": 1894, "file_name": "63cff3304c890df7dfd779f0caf18fd7.jpg", "license": 0, "flickr_url": "", "coco_url": "", "date_captured": 0}, {"id": 3, "width": 1629, "height": 3338, "file_name": "9cffddf11d93ca700a00c776c6f1c37d.jpg", "license": 0, "flickr_url": "", "coco_url": "", "date_captured": 0}, {"id": 4, "width": 2024, "height": 1540, "file_name": "a3f8fdec8249e9e0ff4955bd419cd951.jpg", "license": 0, "flickr_url": "", "coco_url": "", "date_captured": 0}, {"id": 5, "width": 2314, "height": 4547, "file_name": "c0071d689ff09ca2571ea8ee3c33950d.jpg", "license": 0, "flickr_url": "", "coco_url": "", "date_captured": 0}], "annotations": [{"id": 1, "image_id": 1, "category_id": 1, "segmentation": [[2072.47, 1131.01, 1561.8, 1108.76, 1594.16, 1806.52, 2127.59, 1829.78]], "area": 363521.0, "bbox": [1561.8, 1108.76, 565.79, 721.02], "iscrowd": 0, "attributes": {"occluded": false}}, {"id": 2, "image_id": 1, "category_id": 4, "segmentation": [[1004.78, 998.85, 1013.78, 997.29, 1016.06, 1012.64, 1017.19, 1059.85, 1028.57, 1836.69, 1012.28, 1835.71]], "area": 11651.0, "bbox": [1004.78, 997.29, 23.79, 839.4], "iscrowd": 0, "attributes": {"wall frame": true, "window apron": false, "window header": false, "occluded": false}}, {"id": 3, "image_id": 1, "category_id": 4, "segmentation": [[323.53, 969.63, 323.33, 901.9, 1038.48, 933.16, 1013.78, 997.29, 1004.78, 998.85]], "area": 47263.0, "bbox": [323.33, 901.9, 715.15, 96.95], "iscrowd": 0, "attributes": {"wall frame": false, "window apron": false, "window header": true, "occluded": false}}, {"id": 4, "image_id": 1, "category_id": 4, "segmentation": [[1038.48, 933.16, 1041.9, 1034.0, 1050.59, 1626.79, 1055.72, 1836.89, 1028.57, 1836.69, 1017.19, 1059.85, 1016.06, 1012.64, 1013.78, 997.29]], "area": 22207.0, "bbox": [1013.78, 933.16, 41.94, 903.73], "iscrowd": 0, "attributes": {"wall frame": true, "window apron": false, "window header": false, "occluded": false}}, {"id": 5, "image_id": 1, "category_id": 4, "segmentation": [[1055.72, 1836.89, 1058.49, 1850.32, 1056.51, 1860.98, 1050.98, 1862.96, 774.14, 1850.32, 319.97, 1832.55, 305.36, 1825.44, 299.43, 1817.94, 297.85, 1803.72, 330.24, 1804.11, 333.0, 1802.14, 983.06, 1831.36, 983.85, 1834.13, 1012.28, 1835.71, 1028.57, 1836.69]], "area": 21776.0, "bbox": [297.85, 1802.14, 760.64, 60.82], "iscrowd": 0, "attributes": {"wall frame": false, "window apron": true, "window header": false, "occluded": false}}, {"id": 6, "image_id": 1, "category_id": 4, "segmentation": [[2222.26, 1884.46, 2237.75, 1886.65, 2229.06, 1802.14, 2168.24, 1140.24, 2161.13, 1048.61, 2151.75, 1057.57]], "area": 9733.0, "bbox": [2151.75, 1048.61, 86.0, 838.04], "iscrowd": 0, "attributes": {"wall frame": true, "window apron": false, "window header": false, "occluded": false}}, {"id": 7, "image_id": 1, "category_id": 4, "segmentation": [[2161.13, 1048.61, 2108.05, 1046.48, 2085.78, 1047.9, 1787.68, 1034.63, 1511.39, 1018.99, 1512.53, 1028.0, 2151.75, 1057.57]], "area": 4590.0, "bbox": [1511.39, 1018.99, 649.74, 38.58], "iscrowd": 0, "attributes": {"wall frame": false, "window apron": false, "window header": true, "occluded": false}}, {"id": 8, "image_id": 1, "category_id": 4, "segmentation": [[2161.13, 1048.61, 2209.07, 989.53, 2088.2, 983.64, 2072.48, 983.64, 1506.44, 957.1, 1511.39, 1018.99, 1787.68, 1034.63, 2085.78, 1047.9, 2108.05, 1046.48]], "area": 42768.0, "bbox": [1506.44, 957.1, 702.63, 91.51], "iscrowd": 0, "attributes": {"wall frame": false, "window apron": false, "window header": true, "occluded": false}}, {"id": 9, "image_id": 1, "category_id": 4, "segmentation": [[2209.07, 989.53, 2214.64, 1006.73, 2279.34, 1699.54, 2297.36, 1888.71, 2237.75, 1886.65, 2229.06, 1802.14, 2168.24, 1140.24, 2161.13, 1048.61]], "area": 51569.0, "bbox": [2161.13, 989.53, 136.23, 899.18], "iscrowd": 0, "attributes": {"wall frame": true, "window apron": false, "window header": false, "occluded": false}}, {"id": 10, "image_id": 1, "category_id": 4, "segmentation": [[2297.36, 1888.71, 2308.4, 1889.08, 2307.93, 1899.56, 2294.59, 1906.7, 2286.5, 1914.0, 2132.23, 1909.08, 1782.59, 1892.26, 1745.29, 1896.06, 1735.76, 1892.57, 1594.99, 1884.16, 1552.77, 1885.59, 1546.1, 1875.27, 1548.17, 1871.31, 1547.05, 1863.53, 1550.63, 1858.3, 1558.03, 1853.75, 1936.78, 1871.95, 2222.26, 1884.46, 2237.75, 1886.65]], "area": 21266.0, "bbox": [1546.1, 1853.75, 762.3, 60.25], "iscrowd": 0, "attributes": {"wall frame": false, "window apron": true, "window header": false, "occluded": false}}, {"id": 11, "image_id": 1, "category_id": 5, "segmentation": [[2899.0, 1024.21, 2899.0, 744.9, 0.0, 604.99, 0.0, 888.67, 323.33, 901.9, 1038.48, 933.16, 1506.44, 957.1, 2072.48, 983.64, 2088.2, 983.64, 2209.07, 989.53]], "area": 809893.0, "bbox": [0.0, 604.99, 2899.0, 419.22], "iscrowd": 0, "attributes": {"occluded": false}}, {"id": 12, "image_id": 1, "category_id": 2, "segmentation": [[1004.78, 998.85, 1012.28, 1835.71, 922.39, 1775.72, 919.48, 1076.02]], "area": 67362.0, "bbox": [919.48, 998.85, 92.8, 836.86], "iscrowd": 0, "attributes": {"occluded": false}}, {"id": 13, "image_id": 1, "category_id": 1, "segmentation": [[919.48, 1076.02, 404.72, 1051.99, 385.79, 1750.96, 922.39, 1775.72]], "area": 367802.0, "bbox": [385.79, 1051.99, 536.6, 723.73], "iscrowd": 0, "attributes": {"occluded": false}}, {"id": 14, "image_id": 1, "category_id": 2, "segmentation": [[1004.78, 998.85, 323.53, 969.63, 297.85, 1803.72, 330.24, 1804.11, 333.0, 1802.14, 983.06, 1831.36, 983.85, 1834.13, 1012.28, 1835.71, 922.39, 1775.72, 385.79, 1750.96, 404.72, 1051.99, 919.48, 1076.02]], "area": 146137.0, "bbox": [297.85, 969.63, 714.43, 866.08], "iscrowd": 0, "attributes": {"occluded": false}}, {"id": 15, "image_id": 1, "category_id": 5, "segmentation": [[2209.07, 989.53, 2899.0, 1024.21, 2899.0, 2682.0, 0.0, 2682.0, 0.0, 888.67, 323.33, 901.9, 323.53, 969.63, 297.85, 1803.72, 299.43, 1817.94, 305.36, 1825.44, 319.97, 1832.55, 774.14, 1850.32, 1050.98, 1862.96, 1056.51, 1860.98, 1058.49, 1850.32, 1055.72, 1836.89, 1050.59, 1626.79, 1041.9, 1034.0, 1038.48, 933.16, 1506.44, 957.1, 1511.39, 1018.99, 1512.53, 1028.0, 1546.08, 1856.02, 1550.63, 1858.3, 1547.05, 1863.53, 1548.17, 1871.31, 1546.1, 1875.27, 1552.77, 1885.59, 1594.99, 1884.16, 1735.76, 1892.57, 1745.29, 1896.06, 1782.59, 1892.26, 2132.23, 1909.08, 2286.5, 1914.0, 2294.59, 1906.7, 2307.93, 1899.56, 2308.4, 1889.08, 2297.36, 1888.71, 2279.34, 1699.54, 2214.64, 1006.73]], "area": 3652257.0, "bbox": [0.0, 888.67, 2899.0, 1793.33], "iscrowd": 0, "attributes": {"occluded": false}}, {"id": 16, "image_id": 1, "category_id": 2, "segmentation": [[1512.53, 1028.0, 2151.75, 1057.57, 2222.26, 1884.46, 1936.78, 1871.95, 1558.03, 1853.75, 1550.63, 1858.3, 1546.08, 1856.02, 1594.16, 1806.52, 2127.59, 1829.78, 2072.47, 1131.01, 1561.8, 1108.76]], "area": 141879.0, "bbox": [1512.53, 1028.0, 709.73, 856.46], "iscrowd": 0, "attributes": {"occluded": false}}, {"id": 17, "image_id": 1, "category_id": 2, "segmentation": [[1561.8, 1108.76, 1594.16, 1806.52, 1546.08, 1856.02, 1512.53, 1028.0]], "area": 36633.0, "bbox": [1512.53, 1028.0, 81.63, 828.02], "iscrowd": 0, "attributes": {"occluded": false}}, {"id": 18, "image_id": 2, "category_id": 5, "segmentation": [[495.61, 59.08, 494.33, 0.0, 1385.24, 0.0, 2815.74, 219.02, 2842.49, 273.58, 2891.71, 284.28, 2902.86, 302.32, 2811.54, 279.92, 2801.09, 279.67, 2749.33, 291.12, 2723.2, 282.66, 2152.38, 298.58, 1859.01, 292.61, 1851.3, 294.08, 1722.45, 291.42, 1674.13, 289.63, 1579.97, 273.58, 1208.71, 226.51, 789.42, 160.96]], "area": 411158.0, "bbox": [494.33, 0.0, 2408.53, 302.32], "iscrowd": 0, "attributes": {"occluded": false}}, {"id": 19, "image_id": 2, "category_id": 4, "segmentation": [[1664.0, 349.8, 1688.49, 322.18, 1703.97, 854.15, 1728.22, 1216.89, 1743.7, 1597.16, 1741.12, 1645.15, 1738.5, 1730.7, 1715.5, 1727.7]], "area": 37610.0, "bbox": [1664.0, 322.18, 79.7, 1408.52], "iscrowd": 0, "attributes": {"wall frame": true, "window apron": false, "window header": false, "occluded": false}}, {"id": 20, "image_id": 2, "category_id": 4, "segmentation": [[1738.5, 1730.7, 1773.0, 1735.3, 1722.45, 291.42, 1688.49, 322.18, 1703.97, 854.15, 1728.22, 1216.89, 1743.7, 1597.16, 1741.12, 1645.15]], "area": 45488.0, "bbox": [1688.49, 291.42, 84.51, 1443.88], "iscrowd": 0, "attributes": {"wall frame": true, "window apron": false, "window header": false, "occluded": false}}, {"id": 21, "image_id": 2, "category_id": 4, "segmentation": [[1688.49, 322.18, 802.56, 192.7, 819.7, 225.24, 881.44, 234.21, 910.52, 239.6, 1253.7, 290.21, 1664.0, 349.8]], "area": 26940.0, "bbox": [802.56, 192.7, 885.93, 157.1], "iscrowd": 0, "attributes": {"wall frame": false, "window apron": false, "window header": true, "occluded": false}}, {"id": 22, "image_id": 2, "category_id": 4, "segmentation": [[1722.45, 291.42, 1674.13, 289.63, 1579.97, 273.58, 1208.71, 226.51, 789.42, 160.96, 802.56, 192.7, 1688.49, 322.18]], "area": 26209.0, "bbox": [789.42, 160.96, 933.03, 161.22], "iscrowd": 0, "attributes": {"wall frame": false, "window apron": false, "window header": true, "occluded": false}}, {"id": 23, "image_id": 2, "category_id": 4, "segmentation": [[802.56, 192.7, 801.57, 245.05, 823.11, 757.73, 804.45, 711.27, 815.0, 1037.7, 837.23, 1069.79, 853.1, 1608.8, 866.0, 1610.5, 865.29, 1588.98, 872.11, 1583.59, 868.88, 1464.77, 861.34, 1463.34, 826.2, 408.61, 834.38, 407.86, 829.92, 290.25, 821.73, 288.76, 819.7, 225.24]], "area": 27682.0, "bbox": [801.57, 192.7, 70.54, 1417.8], "iscrowd": 0, "attributes": {"wall frame": true, "window apron": false, "window header": false, "occluded": false}}, {"id": 24, "image_id": 2, "category_id": 4, "segmentation": [[853.1, 1608.8, 833.38, 1606.11, 815.0, 1037.7, 837.23, 1069.79]], "area": 11335.0, "bbox": [815.0, 1037.7, 38.1, 571.1], "iscrowd": 0, "attributes": {"wall frame": true, "window apron": false, "window header": false, "occluded": false}}, {"id": 25, "image_id": 2, "category_id": 4, "segmentation": [[789.42, 160.96, 802.56, 192.7, 801.57, 245.05, 823.11, 757.73, 804.45, 711.27]], "area": 7407.0, "bbox": [789.42, 160.96, 33.69, 596.77], "iscrowd": 0, "attributes": {"wall frame": true, "window apron": false, "window header": false, "occluded": false}}, {"id": 26, "image_id": 2, "category_id": 1, "segmentation": [[1858.44, 330.57, 1749.15, 326.99, 1798.96, 1738.76, 2017.89, 1767.43, 2048.71, 1686.45, 2062.32, 1576.09, 2059.82, 1520.91, 2045.84, 1429.18, 2033.3, 1375.07, 2011.08, 1308.42, 1995.32, 1248.58, 1981.7, 1160.08, 1951.6, 984.15, 1924.01, 863.03, 1913.98, 760.2, 1903.95, 692.47, 1893.2, 571.0, 1875.6, 459.6, 1864.53, 368.55]], "area": 270537.0, "bbox": [1749.15, 326.99, 313.17, 1440.44], "iscrowd": 0, "attributes": {"occluded": false}}, {"id": 27, "image_id": 2, "category_id": 5, "segmentation": [[38.48, 1398.19, 0.0, 1391.6, 0.0, 0.0, 20.65, 0.0, 56.32, 1377.39]], "area": 53892.0, "bbox": [0.0, 0.0, 56.32, 1398.19], "iscrowd": 0, "attributes": {"occluded": false}}, {"id": 28, "image_id": 2, "category_id": 1, "segmentation": [[2657.36, 323.59, 2184.21, 339.59, 2245.1, 1786.91, 2722.89, 1772.46]], "area": 689396.0, "bbox": [2184.21, 323.59, 538.68, 1463.32], "iscrowd": 0, "attributes": {"occluded": false}}, {"id": 29, "image_id": 2, "category_id": 1, "segmentation": [[1601.84, 412.28, 1303.77, 367.35, 1352.39, 1654.33, 1649.49, 1693.06]], "area": 379956.0, "bbox": [1303.77, 367.35, 345.72, 1325.71], "iscrowd": 0, "attributes": {"occluded": false}}, {"id": 30, "image_id": 2, "category_id": 2, "segmentation": [[819.7, 225.24, 821.73, 288.76, 829.92, 290.25, 834.38, 407.86, 826.2, 408.61, 861.34, 1463.34, 868.88, 1464.77, 931.56, 1596.23, 887.39, 307.06]], "area": 80927.0, "bbox": [819.7, 225.24, 111.86, 1370.99], "iscrowd": 0, "attributes": {"occluded": false}}, {"id": 31, "image_id": 2, "category_id": 5, "segmentation": [[2982.13, 1894.0, 2974.02, 1804.27, 2871.51, 1789.58, 2761.27, 1795.56, 2741.12, 1775.9, 2735.64, 1784.36, 2732.16, 1797.05, 2325.07, 1809.49, 2577.7, 1843.73, 2877.28, 1884.38]], "area": 35139.0, "bbox": [2325.07, 1775.9, 657.06, 118.1], "iscrowd": 0, "attributes": {"occluded": false}}, {"id": 32, "image_id": 2, "category_id": 5, "segmentation": [[2902.86, 302.32, 3015.0, 321.57, 3015.0, 1812.34, 2974.02, 1804.27]], "area": 114118.0, "bbox": [2902.86, 302.32, 112.14, 1510.02], "iscrowd": 0, "attributes": {"occluded": false}}, {"id": 33, "image_id": 2, "category_id": 5, "segmentation": [[2902.86, 302.32, 2911.74, 300.89, 2909.68, 292.12, 2901.94, 70.25, 2916.9, 65.09, 2901.94, 9.36, 2899.87, 0.0, 3015.0, 0.0, 3015.0, 321.57]], "area": 33875.0, "bbox": [2899.87, 0.0, 115.13, 321.57], "iscrowd": 0, "attributes": {"occluded": false}}, {"id": 34, "image_id": 2, "category_id": 2, "segmentation": [[2720.22, 319.98, 2784.66, 1768.19, 2722.89, 1772.46, 2657.36, 323.59]], "area": 90494.0, "bbox": [2657.36, 319.98, 127.3, 1452.48], "iscrowd": 0, "attributes": {"occluded": false}}, {"id": 35, "image_id": 2, "category_id": 2, "segmentation": [[1866.35, 331.88, 1859.01, 292.61, 2152.38, 298.58, 2723.2, 282.66, 2749.33, 291.12, 2801.09, 279.67, 2811.54, 279.92, 2902.86, 302.32, 2974.02, 1804.27, 2871.51, 1789.58, 2761.27, 1795.56, 2741.12, 1775.9, 2735.64, 1784.36, 2732.16, 1797.05, 2325.07, 1809.49, 2176.23, 1790.2, 2245.1, 1786.91, 2722.89, 1772.46, 2784.66, 1768.19, 2944.17, 1776.89, 2877.48, 328.94, 2804.82, 317.74, 2720.22, 319.98, 2657.36, 323.59, 2184.21, 339.59, 2119.84, 340.08]], "area": 97921.0, "bbox": [1859.01, 279.67, 1115.01, 1529.82], "iscrowd": 0, "attributes": {"occluded": false}}, {"id": 36, "image_id": 2, "category_id": 2, "segmentation": [[2184.21, 339.59, 2245.1, 1786.91, 2176.23, 1790.2, 2119.84, 340.08]], "area": 96727.0, "bbox": [2119.84, 339.59, 125.26, 1450.61], "iscrowd": 0, "attributes": {"occluded": false}}, {"id": 37, "image_id": 2, "category_id": 5, "segmentation": [[789.42, 160.96, 495.61, 59.08, 533.06, 1549.5, 655.03, 1579.45, 833.38, 1606.11, 804.45, 711.27]], "area": 432646.0, "bbox": [495.61, 59.08, 337.77, 1547.03], "iscrowd": 0, "attributes": {"occluded": false}}, {"id": 38, "image_id": 2, "category_id": 2, "segmentation": [[1851.3, 294.08, 1722.45, 291.42, 1773.0, 1735.3, 1798.96, 1738.76, 1749.15, 326.99, 1858.44, 330.57]], "area": 40957.0, "bbox": [1722.45, 291.42, 135.99, 1447.34], "iscrowd": 0, "attributes": {"occluded": false}}, {"id": 39, "image_id": 2, "category_id": 5, "segmentation": [[235.62, 1811.63, 251.87, 1821.99, 314.82, 1842.63, 558.36, 1894.0, 237.8, 1894.0]], "area": 11313.0, "bbox": [235.62, 1811.63, 322.74, 82.37], "iscrowd": 0, "attributes": {"occluded": false}}, {"id": 40, "image_id": 2, "category_id": 9, "segmentation": [[1866.35, 331.88, 1859.01, 292.61, 1851.3, 294.08, 1858.44, 330.57, 1864.53, 368.55, 1875.6, 459.6, 1893.2, 571.0, 1903.95, 692.47, 1913.98, 760.2, 1924.01, 863.03, 1951.6, 984.15, 1981.7, 1160.08, 1995.32, 1248.58, 2011.08, 1308.42, 2033.3, 1375.07, 2045.84, 1429.18, 2059.82, 1520.91, 2062.32, 1576.09, 2048.71, 1686.45, 2017.89, 1767.43, 2022.01, 1768.03, 2052.37, 1688.03, 2067.79, 1575.26, 2065.38, 1521.29, 2051.41, 1427.79, 2039.36, 1373.82, 2016.71, 1305.38, 2000.81, 1247.55, 1987.79, 1159.36, 1957.43, 983.45, 1930.93, 859.11, 1922.25, 761.76, 1912.13, 692.37, 1901.05, 571.4, 1884.18, 458.63, 1872.13, 364.17]], "area": 9822.0, "bbox": [1851.3, 292.61, 216.49, 1475.42], "iscrowd": 0, "attributes": {"occluded": false}}, {"id": 41, "image_id": 2, "category_id": 1, "segmentation": [[2720.22, 319.98, 2784.66, 1768.19, 2944.17, 1776.89, 2877.48, 328.94, 2804.82, 317.74]], "area": 229342.0, "bbox": [2720.22, 317.74, 223.95, 1459.15], "iscrowd": 0, "attributes": {"occluded": false}}, {"id": 42, "image_id": 2, "category_id": 5, "segmentation": [[2982.13, 1894.0, 2877.28, 1884.38, 2577.7, 1843.73, 2325.07, 1809.49, 2176.23, 1790.2, 2022.01, 1768.03, 2017.89, 1767.43, 1798.96, 1738.76, 1640.16, 1717.56, 1368.35, 1676.69, 1173.31, 1650.07, 934.92, 1619.73, 833.38, 1606.11, 655.03, 1579.45, 209.94, 1518.47, 35.54, 1451.92, 40.89, 1736.52, 53.73, 1768.62, 72.99, 1778.46, 125.42, 1773.11, 150.02, 1800.93, 163.93, 1776.32, 235.62, 1811.63, 251.87, 1821.99, 314.82, 1842.63, 558.36, 1894.0]], "area": 548794.0, "bbox": [35.54, 1451.92, 2946.59, 442.08], "iscrowd": 0, "attributes": {"occluded": false}}, {"id": 43, "image_id": 2, "category_id": 5, "segmentation": [[215.72, 1395.64, 210.86, 1445.0, 140.28, 1412.31, 38.48, 1398.19, 42.94, 1390.02, 56.32, 1377.39, 20.65, 0.0, 177.2, 0.0, 183.62, 328.7, 205.45, 984.79]], "area": 222970.0, "bbox": [20.65, 0.0, 195.07, 1445.0], "iscrowd": 0, "attributes": {"occluded": false}}, {"id": 44, "image_id": 2, "category_id": 5, "segmentation": [[533.06, 1549.5, 477.64, 1511.19, 423.71, 1448.28, 409.59, 1429.02, 356.95, 1418.75, 252.95, 1421.32, 233.69, 1411.05, 219.57, 1416.18, 215.72, 1395.64, 205.45, 984.79, 183.62, 328.7, 177.2, 0.0, 494.33, 0.0, 495.61, 59.08]], "area": 457636.0, "bbox": [177.2, 0.0, 355.86, 1549.5], "iscrowd": 0, "attributes": {"occluded": false}}, {"id": 45, "image_id": 2, "category_id": 2, "segmentation": [[1303.77, 367.35, 1352.39, 1654.33, 1233.57, 1635.18, 1185.78, 350.04]], "area": 151390.0, "bbox": [1185.78, 350.04, 166.61, 1304.29], "iscrowd": 0, "attributes": {"occluded": false}}, {"id": 46, "image_id": 2, "category_id": 2, "segmentation": [[819.7, 225.24, 881.44, 234.21, 910.52, 239.6, 1253.7, 290.21, 1664.0, 349.8, 1715.5, 1727.6, 1640.16, 1717.56, 1368.35, 1676.69, 1173.31, 1650.07, 934.92, 1619.73, 866.0, 1610.5, 865.29, 1588.98, 872.11, 1583.59, 868.88, 1464.77, 931.56, 1596.23, 1233.57, 1635.18, 1352.39, 1654.33, 1649.49, 1693.06, 1601.84, 412.28, 1303.77, 367.35, 1185.78, 350.04, 887.39, 307.06]], "area": 163282.0, "bbox": [819.7, 225.24, 895.8, 1502.36], "iscrowd": 0, "attributes": {"occluded": false}}, {"id": 47, "image_id": 2, "category_id": 5, "segmentation": [[2902.86, 302.32, 2891.71, 284.28, 2842.49, 273.58, 2815.74, 219.02, 1385.24, 0.0, 2899.87, 0.0, 2901.94, 9.36, 2916.9, 65.09, 2901.94, 70.25, 2909.68, 292.12, 2911.74, 300.89]], "area": 181308.0, "bbox": [1385.24, 0.0, 1531.66, 302.32], "iscrowd": 0, "attributes": {"occluded": false}}, {"id": 48, "image_id": 2, "category_id": 5, "segmentation": [[72.99, 1778.46, 125.42, 1773.11, 150.02, 1800.93, 163.93, 1776.32, 235.62, 1811.63, 237.8, 1894.0, 74.1, 1894.0]], "area": 17490.0, "bbox": [72.99, 1773.11, 164.81, 120.89], "iscrowd": 0, "attributes": {"occluded": false}}, {"id": 49, "image_id": 2, "category_id": 1, "segmentation": [[2119.84, 340.08, 1866.35, 331.88, 1872.13, 364.17, 1884.18, 458.63, 1901.05, 571.4, 1912.13, 692.37, 1922.25, 761.76, 1930.93, 859.11, 1957.43, 983.45, 1987.79, 1159.36, 2000.81, 1247.55, 2016.71, 1305.38, 2039.36, 1373.82, 2051.41, 1427.79, 2065.38, 1521.29, 2067.79, 1575.26, 2052.37, 1688.03, 2022.01, 1768.03, 2176.23, 1790.2]], "area": 252970.0, "bbox": [1866.35, 331.88, 309.88, 1458.32], "iscrowd": 0, "attributes": {"occluded": false}}, {"id": 50, "image_id": 2, "category_id": 5, "segmentation": [[0.0, 1762.2, 0.0, 1894.0, 74.1, 1894.0, 72.99, 1778.46, 53.73, 1768.62]], "area": 9302.0, "bbox": [0.0, 1762.2, 74.1, 131.8], "iscrowd": 0, "attributes": {"occluded": false}}, {"id": 51, "image_id": 2, "category_id": 5, "segmentation": [[40.89, 1736.52, 35.54, 1451.92, 26.98, 1444.43, 23.77, 1423.03, 13.9, 1394.0, 0.0, 1391.6, 0.0, 1762.2, 53.73, 1768.62]], "area": 13566.0, "bbox": [0.0, 1391.6, 53.73, 377.02], "iscrowd": 0, "attributes": {"occluded": false}}, {"id": 52, "image_id": 2, "category_id": 1, "segmentation": [[1185.78, 350.04, 887.39, 307.06, 931.56, 1596.23, 1233.57, 1635.18]], "area": 384531.0, "bbox": [887.39, 307.06, 346.18, 1328.12], "iscrowd": 0, "attributes": {"occluded": false}}, {"id": 53, "image_id": 2, "category_id": 5, "segmentation": [[2974.02, 1804.27, 2982.13, 1894.0, 3015.0, 1894.0, 3015.0, 1812.34]], "area": 3148.0, "bbox": [2974.02, 1804.27, 40.98, 89.73], "iscrowd": 0, "attributes": {"occluded": false}}, {"id": 54, "image_id": 2, "category_id": 5, "segmentation": [[655.03, 1579.45, 533.06, 1549.5, 477.64, 1511.19, 423.71, 1448.28, 409.59, 1429.02, 356.95, 1418.75, 252.95, 1421.32, 233.69, 1411.05, 219.57, 1416.18, 215.72, 1395.64, 210.86, 1445.0, 140.28, 1412.31, 38.48, 1398.19, 13.9, 1394.0, 23.77, 1423.03, 26.98, 1444.43, 35.54, 1451.92, 209.94, 1518.47]], "area": 43159.0, "bbox": [13.9, 1394.0, 641.13, 185.45], "iscrowd": 0, "attributes": {"occluded": false}}, {"id": 55, "image_id": 3, "category_id": 1, "segmentation": [[432.57, 1315.28, 1127.56, 1247.35, 1097.25, 1634.84, 398.61, 1700.94]], "area": 267230.0, "bbox": [398.61, 1247.35, 728.95, 453.59], "iscrowd": 0, "attributes": {"occluded": false}}, {"id": 56, "image_id": 3, "category_id": 4, "segmentation": [[150.33, 1028.53, 536.02, 988.98, 1336.67, 910.41, 1176.18, 1103.0, 1173.14, 1150.61, 1003.56, 1169.04, 851.6, 1182.15, 572.66, 1210.41, 389.98, 1226.8, 343.28, 1231.71]], "area": 222615.0, "bbox": [150.33, 910.41, 1186.34, 321.3], "iscrowd": 0, "attributes": {"wall frame": false, "window apron": false, "window header": true, "occluded": false}}, {"id": 57, "image_id": 3, "category_id": 4, "segmentation": [[1173.14, 1150.61, 1176.18, 1103.0, 1336.67, 910.41, 1353.36, 927.1, 1313.56, 1461.21, 1276.32, 2004.31, 1244.23, 2489.63, 1226.25, 2720.73, 1050.67, 2736.6, 1092.04, 2204.53, 1140.78, 1565.13, 1147.33, 1474.61, 1167.41, 1248.1]], "area": 291644.0, "bbox": [1050.67, 910.41, 302.69, 1826.19], "iscrowd": 0, "attributes": {"wall frame": true, "window apron": false, "window header": false, "occluded": false}}, {"id": 58, "image_id": 3, "category_id": 5, "segmentation": [[1257.77, 2757.16, 1558.39, 2740.67, 1578.9, 2752.62, 1596.02, 2746.2, 1582.89, 2722.64, 1555.2, 2714.12, 1263.72, 2730.42]], "area": 8775.0, "bbox": [1257.77, 2714.12, 338.25, 43.04], "iscrowd": 0, "attributes": {"occluded": false}}, {"id": 59, "image_id": 3, "category_id": 5, "segmentation": [[1629.0, 364.1, 982.69, 445.12, 931.34, 455.39, 671.98, 478.5, 0.0, 550.4, 0.0, 249.45, 659.89, 173.64, 693.17, 132.97, 768.97, 95.99, 887.3, 77.5, 935.37, 88.6, 1020.41, 134.82, 1629.0, 64.56]], "area": 513768.0, "bbox": [0.0, 64.56, 1629.0, 485.84], "iscrowd": 0, "attributes": {"occluded": false}}, {"id": 60, "image_id": 3, "category_id": 1, "segmentation": [[1046.6, 2232.9, 750.6, 2256.9, 708.65, 2686.63, 1010.12, 2663.69]], "area": 127593.0, "bbox": [708.65, 2232.9, 337.95, 453.73], "iscrowd": 0, "attributes": {"occluded": false}}, {"id": 61, "image_id": 3, "category_id": 5, "segmentation": [[0.0, 138.52, 0.0, 249.45, 659.89, 173.64, 693.17, 132.97, 768.97, 95.99, 887.3, 77.5, 935.37, 88.6, 1020.41, 134.82, 1629.0, 64.56, 1629.0, 0.0, 1249.67, 0.0]], "area": 151171.0, "bbox": [0.0, 0.0, 1629.0, 249.45], "iscrowd": 0, "attributes": {"occluded": false}}, {"id": 62, "image_id": 3, "category_id": 5, "segmentation": [[1268.62, 3282.23, 1361.71, 3338.0, 406.26, 3338.0]], "area": 26675.0, "bbox": [406.26, 3282.23, 955.45, 55.77], "iscrowd": 0, "attributes": {"occluded": false}}, {"id": 63, "image_id": 3, "category_id": 5, "segmentation": [[0.0, 550.4, 671.98, 478.5, 931.34, 455.39, 982.69, 445.12, 1629.0, 364.1, 1629.0, 591.48, 1466.34, 614.85, 969.4, 672.4, 0.0, 776.75]], "area": 368821.0, "bbox": [0.0, 364.1, 1629.0, 412.65], "iscrowd": 0, "attributes": {"occluded": false}}, {"id": 64, "image_id": 3, "category_id": 5, "segmentation": [[0.0, 884.29, 35.4, 913.39, 39.73, 914.63, 51.5, 925.77, 47.78, 961.68, 103.51, 1007.5, 130.13, 1009.98, 139.42, 1012.46, 145.61, 1021.74, 150.33, 1028.53, 125.93, 1278.89, 50.18, 1994.04, 0.0, 2466.52]], "area": 118727.0, "bbox": [0.0, 884.29, 150.33, 1582.23], "iscrowd": 0, "attributes": {"occluded": false}}, {"id": 65, "image_id": 3, "category_id": 5, "segmentation": [[1533.96, 3338.0, 1533.96, 3307.91, 1550.01, 3294.0, 1599.23, 3256.55, 1547.87, 3196.64, 1171.58, 3217.83, 1014.07, 3225.26, 86.79, 3280.24, 64.5, 3285.44, 0.0, 3292.87, 0.0, 3338.0, 406.26, 3338.0, 1268.62, 3282.23, 1361.71, 3338.0]], "area": 126421.0, "bbox": [0.0, 3196.64, 1599.23, 141.36], "iscrowd": 0, "attributes": {"occluded": false}}, {"id": 66, "image_id": 3, "category_id": 4, "segmentation": [[343.28, 1231.71, 150.33, 1028.53, 125.93, 1278.89, 50.18, 1994.04, 0.0, 2466.52, 0.0, 2811.89, 152.9, 2799.05, 169.59, 2790.06, 174.72, 2809.32, 186.81, 2808.69, 207.3, 2630.75, 214.34, 2547.97, 240.76, 2340.14, 254.85, 2172.83, 284.79, 1887.51, 302.41, 1665.59]], "area": 363384.0, "bbox": [0.0, 1028.53, 343.28, 1783.36], "iscrowd": 0, "attributes": {"wall frame": true, "window apron": false, "window header": false, "occluded": false}}, {"id": 67, "image_id": 3, "category_id": 5, "segmentation": [[1582.89, 2722.64, 1596.02, 2746.2, 1578.9, 2752.62, 1563.92, 2889.57, 1613.14, 2949.48, 1591.74, 2978.37, 1556.43, 3005.12, 1547.87, 3196.64, 1599.23, 3256.55, 1550.01, 3294.0, 1533.96, 3307.91, 1533.96, 3338.0, 1629.0, 3338.0, 1629.0, 2668.06, 1585.02, 2690.69]], "area": 39830.0, "bbox": [1533.96, 2668.06, 95.04, 669.94], "iscrowd": 0, "attributes": {"occluded": false}}, {"id": 68, "image_id": 3, "category_id": 5, "segmentation": [[1257.77, 2757.16, 1558.39, 2740.67, 1578.9, 2752.62, 1563.92, 2889.57, 1613.14, 2949.48, 1591.74, 2978.37, 1556.43, 3005.12, 1547.87, 3196.64, 1171.58, 3217.83, 1184.22, 3205.94, 1191.65, 3175.48, 1202.79, 3147.99, 1185.7, 3139.81, 1189.42, 3124.21, 1188.67, 3097.46, 1186.44, 3075.91, 1185.7, 3041.74, 1186.44, 3020.19, 1181.24, 3010.53, 1175.3, 3002.36, 1188.67, 3001.61, 1197.59, 2991.95, 1200.56, 2970.41, 1201.3, 2944.4, 1203.53, 2931.77, 1209.48, 2924.34, 1221.37, 2868.62]], "area": 164937.0, "bbox": [1171.58, 2740.67, 441.56, 477.16], "iscrowd": 0, "attributes": {"occluded": false}}, {"id": 69, "image_id": 3, "category_id": 1, "segmentation": [[384.52, 1839.63, 675.9, 1816.04, 637.56, 2241.31, 341.46, 2266.08]], "area": 124150.0, "bbox": [341.46, 1816.04, 334.44, 450.04], "iscrowd": 0, "attributes": {"occluded": false}}, {"id": 70, "image_id": 3, "category_id": 1, "segmentation": [[340.82, 2285.63, 634.92, 2261.05, 593.14, 2698.1, 298.22, 2717.76]], "area": 127133.0, "bbox": [298.22, 2261.05, 336.7, 456.71], "iscrowd": 0, "attributes": {"occluded": false}}, {"id": 71, "image_id": 3, "category_id": 5, "segmentation": [[1629.0, 2651.02, 1607.65, 2631.85, 1593.81, 2614.55, 1581.83, 2596.44, 1589.28, 2431.64, 1629.0, 2401.82]], "area": 9200.0, "bbox": [1581.83, 2401.82, 47.17, 249.2], "iscrowd": 0, "attributes": {"occluded": false}}, {"id": 72, "image_id": 3, "category_id": 5, "segmentation": [[1629.0, 2364.29, 1603.39, 2332.07, 1606.59, 2235.96, 1611.91, 2170.73, 1629.0, 2157.69]], "area": 4110.0, "bbox": [1603.39, 2157.69, 25.61, 206.6], "iscrowd": 0, "attributes": {"occluded": false}}, {"id": 73, "image_id": 3, "category_id": 2, "segmentation": [[343.28, 1231.71, 302.41, 1665.59, 284.79, 1887.51, 254.85, 2172.83, 240.76, 2340.14, 214.34, 2547.97, 207.3, 2630.75, 186.81, 2808.69, 298.22, 2717.76, 340.82, 2285.63, 634.92, 2261.05, 750.7, 2256.9, 1046.6, 2232.9, 1049.03, 2205.75, 754.5, 2231.7, 637.56, 2241.31, 341.46, 2266.08, 384.52, 1839.63, 398.61, 1700.94, 432.57, 1315.28]], "area": 161090.0, "bbox": [186.81, 1231.71, 862.22, 1576.98], "iscrowd": 0, "attributes": {"occluded": false}}, {"id": 74, "image_id": 3, "category_id": 2, "segmentation": [[186.81, 2808.69, 839.31, 2767.32, 840.95, 2763.23, 838.9, 2759.13, 839.72, 2756.67, 867.98, 2754.22, 878.22, 2741.52, 922.46, 2747.66, 1050.67, 2736.6, 1092.04, 2204.53, 1140.78, 1565.13, 1147.33, 1474.61, 1167.41, 1248.1, 1173.14, 1150.61, 1003.56, 1169.04, 851.6, 1182.15, 572.66, 1210.41, 389.98, 1226.8, 343.28, 1231.71, 432.57, 1315.28, 1127.56, 1247.35, 1097.25, 1634.84, 398.61, 1700.94, 384.52, 1839.63, 675.9, 1816.04, 637.56, 2241.31, 754.4, 2231.7, 789.3, 1800.2, 1085.48, 1773.21, 1049.03, 2205.75, 1046.6, 2232.9, 1010.12, 2663.69, 708.65, 2686.63, 750.6, 2256.9, 634.92, 2261.05, 593.14, 2698.1, 298.22, 2717.76]], "area": 393015.0, "bbox": [186.81, 1150.61, 986.33, 1658.08], "iscrowd": 0, "attributes": {"occluded": false}}, {"id": 75, "image_id": 3, "category_id": 1, "segmentation": [[1085.48, 1773.21, 789.3, 1800.2, 754.4, 2231.7, 1049.03, 2205.75]], "area": 126653.0, "bbox": [754.4, 1773.21, 331.08, 458.49], "iscrowd": 0, "attributes": {"occluded": false}}, {"id": 76, "image_id": 3, "category_id": 5, "segmentation": [[1629.0, 2087.14, 1617.24, 2074.09, 1629.0, 1897.05]], "area": 1126.0, "bbox": [1617.24, 1897.05, 11.76, 190.09], "iscrowd": 0, "attributes": {"occluded": false}}, {"id": 77, "image_id": 3, "category_id": 4, "segmentation": [[1479.93, 764.17, 1498.51, 757.36, 1495.41, 749.93, 1473.74, 740.02, 1451.45, 718.35, 1414.92, 691.11, 1143.72, 720.21, 622.38, 774.07, 168.52, 821.75, 0.0, 839.71, 0.0, 884.29, 35.4, 913.39, 20.69, 888.25, 27.28, 882.88, 9.1, 869.21, 4.52, 861.34, 181.64, 843.52, 606.94, 797.79, 1195.54, 734.6, 1410.94, 710.27, 1461.75, 760.37]], "area": 32984.0, "bbox": [0.0, 691.11, 1498.51, 222.28], "iscrowd": 0, "attributes": {"wall frame": false, "window apron": false, "window header": true, "occluded": false}}, {"id": 78, "image_id": 3, "category_id": 4, "segmentation": [[1257.77, 2757.16, 1234.95, 2744.61, 1097.78, 2758.37, 887.52, 2778.15, 862.58, 2780.73, 861.29, 2788.04, 805.39, 2796.21, 161.71, 2840.5, 138.49, 2826.74, 0.0, 2838.35, 0.0, 2811.89, 152.9, 2799.05, 169.59, 2790.06, 174.72, 2809.32, 186.81, 2808.69, 839.31, 2767.32, 840.95, 2763.23, 838.9, 2759.13, 839.72, 2756.67, 867.98, 2754.22, 878.22, 2741.52, 922.46, 2747.66, 1050.67, 2736.6, 1226.25, 2720.73, 1236.23, 2720.76, 1242.17, 2722.99, 1255.54, 2712.58, 1263.72, 2730.42]], "area": 35586.0, "bbox": [0.0, 2712.58, 1263.72, 127.92], "iscrowd": 0, "attributes": {"wall frame": false, "window apron": true, "window header": false, "occluded": false}}, {"id": 79, "image_id": 3, "category_id": 4, "segmentation": [[1257.77, 2757.16, 1234.95, 2744.61, 1097.78, 2758.37, 887.52, 2778.15, 862.58, 2780.73, 861.29, 2788.04, 805.39, 2796.21, 161.71, 2840.5, 138.49, 2826.74, 0.0, 2838.35, 0.0, 3292.87, 64.5, 3285.44, 86.79, 3280.24, 1014.07, 3225.26, 1171.58, 3217.83, 1184.22, 3205.94, 1191.65, 3175.48, 1202.79, 3147.99, 1185.7, 3139.81, 1189.42, 3124.21, 1188.67, 3097.46, 1186.44, 3075.91, 1185.7, 3041.74, 1186.44, 3020.19, 1181.24, 3010.53, 1175.3, 3002.36, 1188.67, 3001.61, 1197.59, 2991.95, 1200.56, 2970.41, 1201.3, 2944.4, 1203.53, 2931.77, 1209.48, 2924.34, 1221.37, 2868.62]], "area": 538796.0, "bbox": [0.0, 2744.61, 1257.77, 548.26], "iscrowd": 0, "attributes": {"wall frame": false, "window apron": true, "window header": false, "occluded": false}}, {"id": 80, "image_id": 3, "category_id": 4, "segmentation": [[1353.36, 927.1, 1365.39, 912.15, 1362.91, 902.86, 1379.01, 878.72, 1403.16, 871.29, 1428.54, 865.09, 1431.64, 839.71, 1441.54, 831.66, 1451.45, 811.23, 1457.02, 785.84, 1463.22, 774.69, 1479.9, 764.2, 1461.75, 760.37, 1410.94, 710.27, 1195.54, 734.6, 606.94, 797.79, 181.64, 843.52, 4.52, 861.34, 9.1, 869.21, 27.28, 882.88, 20.69, 888.25, 35.8, 913.5, 39.73, 914.63, 51.5, 925.77, 47.78, 961.68, 103.51, 1007.5, 130.13, 1009.98, 139.42, 1012.46, 145.61, 1021.74, 150.33, 1028.53, 536.02, 988.98, 1336.67, 910.41]], "area": 255277.0, "bbox": [4.52, 710.27, 1475.38, 318.26], "iscrowd": 0, "attributes": {"wall frame": false, "window apron": false, "window header": true, "occluded": false}}, {"id": 81, "image_id": 3, "category_id": 5, "segmentation": [[0.0, 138.52, 1249.67, 0.0, 0.0, 0.0]], "area": 86585.0, "bbox": [0.0, 0.0, 1249.67, 138.52], "iscrowd": 0, "attributes": {"occluded": false}}, {"id": 82, "image_id": 3, "category_id": 5, "segmentation": [[0.0, 839.71, 168.52, 821.75, 622.38, 774.07, 1143.72, 720.21, 1414.92, 691.11, 1451.45, 718.35, 1473.74, 740.02, 1495.41, 749.93, 1498.51, 757.36, 1479.93, 764.17, 1463.22, 774.69, 1457.02, 785.84, 1451.45, 811.23, 1441.54, 831.66, 1431.64, 839.71, 1428.54, 865.09, 1403.16, 871.29, 1379.01, 878.72, 1362.91, 902.86, 1365.39, 912.15, 1353.36, 927.1, 1313.56, 1461.21, 1276.32, 2004.31, 1244.23, 2489.63, 1226.25, 2720.73, 1236.23, 2720.76, 1242.17, 2722.99, 1255.54, 2712.58, 1263.72, 2730.42, 1555.2, 2714.12, 1582.89, 2722.64, 1585.02, 2690.69, 1629.0, 2668.06, 1629.0, 2651.02, 1607.65, 2631.85, 1593.81, 2614.55, 1581.83, 2596.44, 1589.28, 2431.64, 1629.0, 2401.82, 1629.0, 2364.29, 1603.39, 2332.07, 1606.59, 2235.96, 1611.91, 2170.73, 1629.0, 2157.69, 1629.0, 2087.14, 1617.24, 2074.09, 1629.0, 1897.05, 1629.0, 591.48, 1466.34, 614.85, 969.4, 672.4, 0.0, 776.75]], "area": 750302.0, "bbox": [0.0, 591.48, 1629.0, 2138.94], "iscrowd": 0, "attributes": {"occluded": false}}, {"id": 83, "image_id": 4, "category_id": 4, "segmentation": [[1669.74, 1184.42, 1411.46, 1187.01, 916.63, 1182.88, 510.04, 1179.78, 355.25, 1179.78, 333.64, 1180.41, 326.25, 1176.72, 328.1, 1167.47, 333.64, 1167.47, 335.49, 1139.74, 348.43, 1137.89, 352.13, 1143.44, 412.01, 1143.67, 428.2, 1143.41, 533.13, 1143.47, 913.55, 1145.26, 1136.0, 1144.96, 1518.51, 1147.35, 1617.1, 1147.71, 1631.87, 1148.57, 1657.02, 1148.8, 1660.5, 1142.82, 1677.44, 1142.82, 1675.9, 1162.85]], "area": 51289.0, "bbox": [326.25, 1137.89, 1351.19, 49.12], "iscrowd": 0, "attributes": {"wall frame": false, "window apron": true, "window header": false, "occluded": false}}, {"id": 84, "image_id": 4, "category_id": 4, "segmentation": [[1674.36, 1207.53, 1400.11, 1205.32, 1122.77, 1202.31, 752.12, 1198.01, 615.82, 1195.86, 615.82, 1199.73, 329.95, 1198.9, 333.64, 1180.41, 355.25, 1179.78, 510.04, 1179.78, 916.63, 1182.88, 1411.46, 1187.01, 1669.74, 1184.42]], "area": 24677.0, "bbox": [329.95, 1179.78, 1344.41, 27.75], "iscrowd": 0, "attributes": {"wall frame": false, "window apron": true, "window header": false, "occluded": false}}, {"id": 85, "image_id": 4, "category_id": 5, "segmentation": [[1837.68, 1209.07, 2024.0, 1210.36, 2024.0, 1376.19, 0.0, 1361.22, 0.0, 1196.45, 169.1, 1197.05, 329.95, 1198.9, 615.82, 1199.73, 615.82, 1195.86, 752.12, 1198.01, 1122.77, 1202.31, 1400.11, 1205.32, 1674.36, 1207.53]], "area": 336811.0, "bbox": [0.0, 1195.86, 2024.0, 180.33], "iscrowd": 0, "attributes": {"occluded": false}}, {"id": 86, "image_id": 4, "category_id": 1, "segmentation": [[1517.8, 527.0, 595.3, 520.5, 594.0, 522.6, 574.2, 732.5, 1516.7, 740.7]], "area": 198733.0, "bbox": [574.2, 520.5, 943.6, 220.2], "iscrowd": 0, "attributes": {"occluded": false}}, {"id": 87, "image_id": 4, "category_id": 5, "segmentation": [[169.1, 1197.05, 0.0, 1196.45, 0.0, 0.0, 2024.0, 0.0, 2024.0, 1210.36, 1837.68, 1209.07, 1797.62, 246.13, 1790.39, 106.86, 1353.26, 102.52, 801.57, 99.43, 311.19, 99.43, 250.45, 592.48]], "area": 702057.0, "bbox": [0.0, 0.0, 2024.0, 1210.36], "iscrowd": 0, "attributes": {"occluded": false}}, {"id": 88, "image_id": 4, "category_id": 1, "segmentation": [[1520.5, 870.4, 1146.45, 868.76, 1145.56, 870.55, 1136.0, 1144.96, 1518.51, 1147.35]], "area": 104783.0, "bbox": [1136.0, 868.76, 384.5, 278.59], "iscrowd": 0, "attributes": {"occluded": false}}, {"id": 89, "image_id": 4, "category_id": 5, "segmentation": [[2024.0, 1376.19, 2024.0, 1540.0, 0.0, 1540.0, 0.0, 1361.22]], "area": 346713.0, "bbox": [0.0, 1361.22, 2024.0, 178.78], "iscrowd": 0, "attributes": {"occluded": false}}, {"id": 90, "image_id": 4, "category_id": 1, "segmentation": [[932.06, 866.67, 561.5, 860.99, 559.11, 866.37, 533.13, 1143.47, 913.55, 1145.26]], "area": 105667.0, "bbox": [533.13, 860.99, 398.93, 284.27], "iscrowd": 0, "attributes": {"occluded": false}}, {"id": 91, "image_id": 4, "category_id": 2, "segmentation": [[533.13, 1143.47, 428.2, 1143.41, 430.35, 1100.05, 459.38, 868.22, 462.96, 858.54, 469.41, 852.81, 475.5, 807.66, 476.58, 726.32, 483.74, 681.89, 480.52, 672.58, 485.18, 664.34, 488.76, 654.66, 488.76, 622.41, 491.27, 601.99, 498.08, 577.26, 501.3, 545.02, 494.49, 525.31, 495.21, 507.75, 499.51, 488.04, 497.0, 466.9, 502.02, 437.16, 531.76, 438.24, 938.81, 447.2, 1432.93, 443.97, 1599.55, 443.25, 1608.15, 454.36, 1604.56, 475.14, 1606.71, 506.32, 1608.86, 541.43, 1603.85, 581.56, 1607.79, 746.03, 1607.07, 785.81, 1612.09, 849.23, 1616.03, 927.7, 1618.18, 1039.85, 1618.54, 1075.33, 1614.95, 1120.12, 1617.1, 1147.71, 1518.51, 1147.35, 1520.3, 870.25, 1516.7, 740.7, 1517.8, 527.0, 595.3, 520.5, 594.0, 522.6, 574.2, 732.5, 561.5, 860.99, 559.11, 866.37]], "area": 207414.0, "bbox": [428.2, 437.16, 1190.34, 710.55], "iscrowd": 0, "attributes": {"occluded": false}}, {"id": 92, "image_id": 4, "category_id": 2, "segmentation": [[1520.3, 870.25, 1145.7, 868.7, 1137.4, 1145.4, 1518.51, 1147.35, 1136.0, 1144.96, 913.55, 1145.26, 932.06, 866.67, 561.5, 860.99, 574.2, 732.5, 1516.7, 740.7]], "area": 184593.0, "bbox": [561.5, 732.5, 958.8, 414.85], "iscrowd": 0, "attributes": {"occluded": false}}, {"id": 93, "image_id": 4, "category_id": 4, "segmentation": [[502.02, 437.16, 492.41, 429.21, 491.55, 417.17, 507.46, 411.15, 540.57, 417.6, 615.39, 415.45, 808.88, 417.17, 995.92, 421.9, 1095.68, 416.74, 1260.36, 423.62, 1393.23, 427.49, 1475.35, 424.48, 1508.46, 417.6, 1554.04, 421.04, 1590.59, 416.74, 1601.34, 402.12, 1617.25, 387.93, 1599.55, 443.25, 1432.93, 443.97, 938.81, 447.2, 531.76, 438.24]], "area": 27090.0, "bbox": [491.55, 387.93, 1125.7, 59.27], "iscrowd": 0, "attributes": {"wall frame": false, "window apron": false, "window header": true, "occluded": false}}, {"id": 94, "image_id": 4, "category_id": 4, "segmentation": [[492.41, 429.21, 480.12, 518.3, 458.45, 752.04, 419.75, 1090.52, 412.01, 1143.67, 428.2, 1143.41, 430.35, 1100.05, 459.38, 868.22, 462.96, 858.54, 469.41, 852.81, 475.5, 807.66, 476.58, 726.32, 483.74, 681.89, 480.52, 672.58, 485.18, 664.34, 488.76, 654.66, 488.76, 622.41, 491.27, 601.99, 498.08, 577.26, 501.3, 545.02, 494.49, 525.31, 495.21, 507.75, 499.51, 488.04, 497.0, 466.9, 502.02, 437.16]], "area": 11582.0, "bbox": [412.01, 429.21, 90.01, 714.46], "iscrowd": 0, "attributes": {"wall frame": true, "window apron": false, "window header": false, "occluded": false}}, {"id": 95, "image_id": 4, "category_id": 4, "segmentation": [[1617.25, 387.93, 1619.4, 478.23, 1621.55, 681.61, 1626.71, 977.43, 1631.87, 1148.57, 1617.1, 1147.71, 1614.95, 1120.12, 1618.54, 1075.33, 1618.18, 1039.85, 1616.03, 927.7, 1612.09, 849.23, 1607.07, 785.81, 1607.79, 746.03, 1603.85, 581.56, 1608.86, 541.43, 1606.71, 506.32, 1604.56, 475.14, 1608.15, 454.36, 1599.55, 443.25]], "area": 9920.0, "bbox": [1599.55, 387.93, 32.32, 760.64], "iscrowd": 0, "attributes": {"wall frame": true, "window apron": false, "window header": false, "occluded": false}}, {"id": 96, "image_id": 4, "category_id": 4, "segmentation": [[1617.25, 387.93, 1634.36, 177.44, 1368.73, 174.97, 797.24, 173.11, 462.26, 171.25, 491.55, 417.17, 507.46, 411.15, 540.57, 417.6, 615.39, 415.45, 808.88, 417.17, 995.92, 421.9, 1095.68, 416.74, 1260.36, 423.62, 1393.23, 427.49, 1475.35, 424.48, 1508.46, 417.6, 1554.04, 421.04, 1590.59, 416.74, 1601.34, 402.12]], "area": 281571.0, "bbox": [462.26, 171.25, 1172.1, 256.24], "iscrowd": 0, "attributes": {"wall frame": false, "window apron": false, "window header": true, "occluded": false}}, {"id": 97, "image_id": 4, "category_id": 4, "segmentation": [[462.26, 171.25, 422.39, 511.13, 400.2, 716.35, 352.13, 1143.44, 412.01, 1143.67, 419.75, 1090.52, 458.45, 752.04, 480.12, 518.3, 492.41, 429.21, 491.55, 417.17]], "area": 51461.0, "bbox": [352.13, 171.25, 140.28, 972.42], "iscrowd": 0, "attributes": {"wall frame": true, "window apron": false, "window header": false, "occluded": false}}, {"id": 98, "image_id": 4, "category_id": 4, "segmentation": [[1634.36, 177.44, 1642.9, 496.44, 1651.08, 896.92, 1657.02, 1148.8, 1631.87, 1148.57, 1626.71, 977.43, 1621.55, 681.61, 1619.4, 478.23, 1617.25, 387.93]], "area": 21344.0, "bbox": [1617.25, 177.44, 39.77, 971.36], "iscrowd": 0, "attributes": {"wall frame": true, "window apron": false, "window header": false, "occluded": false}}, {"id": 99, "image_id": 4, "category_id": 4, "segmentation": [[1634.36, 177.44, 1790.39, 106.86, 1353.26, 102.52, 801.57, 99.43, 311.19, 99.43, 462.26, 171.25, 797.24, 173.11, 1368.73, 174.97]], "area": 96538.0, "bbox": [311.19, 99.43, 1479.2, 78.01], "iscrowd": 0, "attributes": {"wall frame": false, "window apron": false, "window header": true, "occluded": false}}, {"id": 100, "image_id": 4, "category_id": 4, "segmentation": [[311.19, 99.43, 250.45, 592.48, 169.1, 1197.05, 329.95, 1198.9, 333.64, 1180.41, 326.25, 1176.72, 328.1, 1167.47, 333.64, 1167.47, 335.49, 1139.74, 348.43, 1137.89, 352.13, 1143.44, 400.2, 716.35, 422.39, 511.13, 462.26, 171.25]], "area": 175805.0, "bbox": [169.1, 99.43, 293.16, 1099.47], "iscrowd": 0, "attributes": {"wall frame": true, "window apron": false, "window header": false, "occluded": false}}, {"id": 101, "image_id": 4, "category_id": 4, "segmentation": [[1790.39, 106.86, 1797.62, 246.13, 1837.68, 1209.07, 1674.36, 1207.53, 1669.74, 1184.42, 1675.9, 1162.85, 1677.44, 1142.82, 1660.5, 1142.82, 1657.02, 1148.8, 1651.08, 896.92, 1642.9, 496.44, 1634.36, 177.44]], "area": 179221.0, "bbox": [1634.36, 106.86, 203.32, 1102.21], "iscrowd": 0, "attributes": {"wall frame": true, "window apron": false, "window header": false, "occluded": false}}, {"id": 102, "image_id": 5, "category_id": 4, "segmentation": [[262.46, 3848.41, 307.94, 3907.7, 425.86, 3971.71, 626.31, 4049.2, 813.29, 4071.1, 966.58, 4091.31, 1487.09, 4189.01, 1820.62, 4236.18, 1958.75, 4249.66, 2044.66, 4217.65, 1900.12, 4085.35, 1871.01, 4114.46, 1806.7, 4075.19, 1118.23, 3928.29, 377.64, 3773.94, 343.11, 3788.16, 317.39, 3775.3]], "area": 312417.0, "bbox": [262.46, 3773.94, 1782.2, 475.72], "iscrowd": 0, "attributes": {"wall frame": false, "window apron": true, "window header": false, "occluded": false}}, {"id": 103, "image_id": 5, "category_id": 4, "segmentation": [[2044.66, 4217.65, 2096.31, 4154.2, 2135.62, 4037.69, 2144.04, 3952.06, 2117.37, 3853.8, 2064.03, 3756.94, 2062.62, 3668.51, 2085.08, 3438.29, 2065.43, 3347.05, 2062.62, 3012.96, 2055.6, 2615.7, 2122.98, 2412.16, 2124.39, 2281.61, 2130.0, 1948.92, 2111.75, 1647.11, 2163.69, 1523.59, 2128.6, 1320.04, 2100.52, 1057.54, 2151.06, 875.06, 2051.39, 846.98, 1845.04, 981.74, 1850.89, 1022.29, 1857.72, 1542.85, 1865.51, 2340.25, 1863.56, 3106.46, 1863.56, 3996.47, 1897.41, 3998.7, 1900.12, 4085.35]], "area": 778406.0, "bbox": [1845.04, 846.98, 318.65, 3370.67], "iscrowd": 0, "attributes": {"wall frame": true, "window apron": false, "window header": false, "occluded": false}}, {"id": 104, "image_id": 5, "category_id": 4, "segmentation": [[2051.39, 846.98, 1886.04, 743.55, 1691.99, 675.63, 1529.47, 610.14, 1325.71, 614.99, 1085.57, 559.2, 886.67, 481.58, 665.93, 391.83, 361.51, 357.47, 474.99, 547.98, 504.47, 557.81, 620.98, 602.73, 936.82, 693.97, 1324.25, 823.12, 1394.44, 837.15, 1524.99, 886.29, 1845.04, 981.74]], "area": 338942.0, "bbox": [361.51, 357.47, 1689.88, 624.27], "iscrowd": 0, "attributes": {"wall frame": false, "window apron": false, "window header": true, "occluded": false}}, {"id": 105, "image_id": 5, "category_id": 5, "segmentation": [[0.0, 0.0, 361.51, 357.47, 280.65, 432.26, 260.44, 543.44, 236.18, 610.14, 246.29, 737.49, 222.03, 860.79, 222.03, 998.25, 209.91, 1180.17, 167.46, 1319.65, 153.31, 1645.09, 155.33, 1816.91, 108.84, 2031.18, 106.82, 2164.59, 100.75, 2336.41, 133.09, 2421.31, 145.22, 2544.61, 153.31, 2629.51, 137.14, 2898.36, 110.86, 3054.0, 98.73, 3286.46, 185.65, 3474.45, 197.78, 3551.27, 171.5, 3646.27, 203.84, 3777.66, 262.46, 3848.41, 307.94, 3907.7, 425.86, 3971.71, 626.31, 4049.2, 813.29, 4071.1, 966.58, 4091.31, 1487.09, 4189.01, 1820.62, 4236.18, 1958.75, 4249.66, 2044.66, 4217.65, 2314.0, 4547.0, 0.0, 4547.0]], "area": 1644873.0, "bbox": [0.0, 0.0, 2314.0, 4547.0], "iscrowd": 0, "attributes": {"occluded": false}}, {"id": 106, "image_id": 5, "category_id": 1, "segmentation": [[910.68, 2851.38, 447.64, 2736.03, 434.64, 3320.92, 428.14, 3586.56, 427.33, 3597.94, 891.18, 3698.67]], "area": 397792.0, "bbox": [427.33, 2736.03, 483.35, 962.64], "iscrowd": 0, "attributes": {"occluded": false}}, {"id": 107, "image_id": 5, "category_id": 5, "segmentation": [[0.0, 0.0, 2314.0, 0.0, 2314.0, 4547.0, 2044.66, 4217.65, 2096.31, 4154.2, 2135.62, 4037.69, 2144.04, 3952.06, 2117.37, 3853.8, 2064.03, 3756.94, 2062.62, 3668.51, 2085.08, 3438.29, 2065.43, 3347.05, 2062.62, 3012.96, 2055.6, 2615.7, 2122.98, 2412.16, 2124.39, 2281.61, 2130.0, 1948.92, 2111.75, 1647.11, 2163.69, 1523.59, 2128.6, 1320.04, 2100.52, 1057.54, 2151.06, 875.06, 2051.39, 846.98, 1886.04, 743.55, 1691.99, 675.63, 1529.47, 610.14, 1325.71, 614.99, 1085.57, 559.2, 886.67, 481.58, 665.93, 391.83, 361.51, 357.47]], "area": 2001405.0, "bbox": [0.0, 0.0, 2314.0, 4547.0], "iscrowd": 0, "attributes": {"occluded": false}}, {"id": 108, "image_id": 5, "category_id": 1, "segmentation": [[1632.33, 1153.21, 1135.97, 998.94, 1135.01, 1128.78, 1121.11, 1774.63, 1629.46, 1916.45]], "area": 387216.0, "bbox": [1121.11, 998.94, 511.22, 917.51], "iscrowd": 0, "attributes": {"occluded": false}}, {"id": 109, "image_id": 5, "category_id": 2, "segmentation": [[1135.97, 998.94, 1135.01, 1128.78, 1121.11, 1774.63, 952.6, 1727.8, 976.08, 953.23]], "area": 128804.0, "bbox": [952.6, 953.23, 183.37, 821.4], "iscrowd": 0, "attributes": {"occluded": false}}, {"id": 110, "image_id": 5, "category_id": 9, "segmentation": [[420.24, 1709.35, 417.9, 1721.05, 419.07, 1736.25, 417.9, 1751.46, 416.73, 1771.35, 415.56, 1788.89, 410.88, 1827.5, 414.39, 1845.04, 414.39, 1861.42, 409.71, 1871.95, 412.05, 1925.76, 412.05, 1940.97, 412.05, 1981.91, 405.04, 2005.3, 406.21, 2038.06, 405.04, 2068.47, 402.7, 2101.23, 398.02, 2145.68, 399.19, 2205.34, 393.34, 2284.88, 393.34, 2380.8, 388.66, 2459.18, 382.81, 2535.22, 382.81, 2580.84, 379.3, 2582.01, 379.3, 2702.5, 373.45, 2793.74, 368.77, 2860.42, 368.77, 2924.76, 368.77, 2963.36, 359.41, 2975.06, 367.6, 3011.32, 357.07, 3080.34, 355.9, 3161.05, 357.07, 3193.81, 353.57, 3224.22, 351.23, 3228.9, 351.23, 3290.9, 341.87, 3446.48, 340.7, 3516.67, 344.21, 3554.1, 339.53, 3598.55, 338.36, 3631.31, 344.21, 3660.55, 344.21, 3669.91, 1671.91, 3954.17, 1735.08, 3917.9, 1730.4, 2034.55, 1704.67, 2028.7, 1704.67, 2052.09, 1678.93, 2046.25, 1678.93, 2073.15, 1677.36, 2937.65, 1641.71, 2997.2, 1624.47, 3862.2, 1076.4, 3740.91, 419.81, 3601.29, 447.64, 2736.03, 450.45, 2637.4, 477.71, 1872.06, 482.24, 1742.1, 483.41, 1690.63, 455.34, 1682.44]], "area": 393515.0, "bbox": [338.36, 1682.44, 1396.72, 2271.73], "iscrowd": 0, "attributes": {"occluded": false}}, {"id": 111, "image_id": 5, "category_id": 2, "segmentation": [[477.71, 1872.06, 482.24, 1742.1, 1678.93, 2073.15, 1677.36, 2937.65, 1550.13, 2908.79, 1554.19, 2160.75, 1518.99, 2154.66, 1104.02, 2035.51, 1092.51, 2796.41, 909.75, 2752.11, 922.91, 1994.76]], "area": 384184.0, "bbox": [477.71, 1742.1, 1201.22, 1195.55], "iscrowd": 0, "attributes": {"occluded": false}}, {"id": 112, "image_id": 5, "category_id": 2, "segmentation": [[1641.71, 2997.2, 1624.47, 3862.2, 1076.4, 3740.91, 1086.14, 3740.91, 1553.25, 3844.08, 1551.62, 3007.36, 1091.02, 2897.69, 910.68, 2851.38, 447.64, 2736.03, 448.5, 2706.8]], "area": 106878.0, "bbox": [447.64, 2706.8, 1194.07, 1155.4], "iscrowd": 0, "attributes": {"occluded": false}}, {"id": 113, "image_id": 5, "category_id": 1, "segmentation": [[1551.62, 3007.36, 1091.02, 2897.69, 1076.4, 3740.91, 1086.14, 3740.91, 1553.25, 3844.08]], "area": 393925.0, "bbox": [1076.4, 2897.69, 476.85, 946.39], "iscrowd": 0, "attributes": {"occluded": false}}, {"id": 114, "image_id": 5, "category_id": 1, "segmentation": [[1554.19, 2160.75, 1518.99, 2154.66, 1104.02, 2035.51, 1092.51, 2796.41, 1550.13, 2908.79]], "area": 342525.0, "bbox": [1092.51, 2035.51, 461.68, 873.28], "iscrowd": 0, "attributes": {"occluded": false}}, {"id": 115, "image_id": 5, "category_id": 9, "segmentation": [[1641.71, 2997.2, 1677.36, 2937.65, 1550.13, 2908.79, 1092.51, 2796.41, 909.75, 2752.11, 470.19, 2643.52, 465.49, 2643.05, 450.45, 2637.4, 448.5, 2706.8]], "area": 81221.0, "bbox": [448.5, 2637.4, 1228.86, 359.8], "iscrowd": 0, "attributes": {"occluded": false}}, {"id": 116, "image_id": 5, "category_id": 1, "segmentation": [[922.91, 1994.76, 477.71, 1872.06, 450.45, 2637.4, 465.49, 2643.05, 470.19, 2643.52, 909.75, 2752.11]], "area": 347090.0, "bbox": [450.45, 1872.06, 472.46, 880.05], "iscrowd": 0, "attributes": {"occluded": false}}, {"id": 117, "image_id": 5, "category_id": 2, "segmentation": [[910.68, 2851.38, 1091.02, 2897.69, 1076.4, 3740.91, 419.81, 3601.29, 447.64, 2736.03, 434.64, 3320.92, 428.14, 3586.56, 427.33, 3597.94, 891.18, 3698.67]], "area": 161000.0, "bbox": [419.81, 2736.03, 671.21, 1004.88], "iscrowd": 0, "attributes": {"occluded": false}}, {"id": 118, "image_id": 5, "category_id": 2, "segmentation": [[460.45, 793.28, 459.55, 760.12, 459.55, 710.02, 462.93, 693.1, 460.9, 670.76, 829.85, 789.23, 1727.5, 1074.91, 1736.97, 1087.09, 1743.07, 1162.91, 1745.1, 1753.22, 1748.48, 1983.39, 1742.39, 2036.87, 1748.48, 2059.88, 1745.77, 2099.15, 1744.42, 2205.43, 1742.39, 2268.39, 1744.42, 2366.55, 1747.13, 2524.95, 1745.1, 2731.43, 1742.39, 2931.81, 1741.03, 3248.62, 1743.07, 3719.11, 1738.33, 3767.85, 1741.71, 3905.95, 1739.68, 3917.46, 1745.77, 3997.34, 1398.49, 3921.52, 758.77, 3784.1, 344.47, 3696.09, 344.21, 3669.91, 1671.91, 3954.17, 1735.08, 3917.9, 1730.4, 2034.55, 1704.67, 2028.7, 1704.67, 2052.09, 1678.93, 2046.25, 1678.93, 2073.15, 482.24, 1742.1, 483.41, 1690.63, 455.34, 1682.44, 420.24, 1709.35, 420.96, 1691.62, 425.02, 1669.95, 420.29, 1658.45, 420.29, 1644.91, 425.02, 1636.78, 426.68, 1578.15, 952.6, 1727.8, 1121.11, 1774.63, 1629.46, 1916.45, 1632.33, 1153.21, 1135.97, 998.94, 976.08, 953.23]], "area": 477538.0, "bbox": [344.21, 670.76, 1404.27, 3326.58], "iscrowd": 0, "attributes": {"occluded": false}}, {"id": 119, "image_id": 5, "category_id": 1, "segmentation": [[976.08, 953.23, 460.45, 793.28, 444.56, 1093.32, 428.66, 1513.57, 426.68, 1578.15, 952.6, 1727.8]], "area": 411777.0, "bbox": [426.68, 793.28, 549.4, 934.52], "iscrowd": 0, "attributes": {"occluded": false}}, {"id": 120, "image_id": 5, "category_id": 4, "segmentation": [[460.9, 670.76, 465.16, 636.42, 466.57, 578.87, 474.99, 547.98, 504.47, 557.81, 620.98, 602.73, 936.82, 693.97, 1324.25, 823.12, 1394.44, 837.15, 1524.99, 886.29, 1845.04, 981.74, 1736.97, 1087.09, 1727.5, 1074.91, 829.85, 789.23]], "area": 167315.0, "bbox": [460.9, 547.98, 1384.14, 539.11], "iscrowd": 0, "attributes": {"wall frame": false, "window apron": false, "window header": true, "occluded": false}}, {"id": 121, "image_id": 5, "category_id": 4, "segmentation": [[1845.04, 981.74, 1850.89, 1022.29, 1857.72, 1542.85, 1865.51, 2340.25, 1863.56, 3106.46, 1863.56, 3996.47, 1822.62, 4014.02, 1745.77, 3997.34, 1739.68, 3917.46, 1741.71, 3905.95, 1738.33, 3767.85, 1743.07, 3719.11, 1741.03, 3248.62, 1742.39, 2931.81, 1745.1, 2731.43, 1747.13, 2524.95, 1744.42, 2366.55, 1742.39, 2268.39, 1744.42, 2205.43, 1745.77, 2099.15, 1748.48, 2059.88, 1742.39, 2036.87, 1748.48, 1983.39, 1745.1, 1753.22, 1743.07, 1162.91, 1736.97, 1087.09]], "area": 351989.0, "bbox": [1736.97, 981.74, 128.54, 3032.28], "iscrowd": 0, "attributes": {"wall frame": true, "window apron": false, "window header": false, "occluded": false}}, {"id": 122, "image_id": 5, "category_id": 4, "segmentation": [[1863.56, 3996.47, 1897.41, 3998.7, 1900.12, 4085.35, 1871.01, 4114.46, 1806.7, 4075.19, 1118.23, 3928.29, 377.64, 3773.94, 343.11, 3788.16, 317.39, 3775.3, 314.0, 3763.79, 315.36, 3730.62, 322.13, 3675.79, 332.28, 3662.92, 344.21, 3660.55, 344.21, 3669.91, 344.47, 3696.09, 758.77, 3784.1, 1398.49, 3921.52, 1745.77, 3997.34, 1822.62, 4014.02]], "area": 110908.0, "bbox": [314.0, 3660.55, 1586.12, 453.91], "iscrowd": 0, "attributes": {"wall frame": false, "window apron": true, "window header": false, "occluded": false}}, {"id": 123, "image_id": 5, "category_id": 4, "segmentation": [[474.99, 547.98, 361.51, 357.47, 280.65, 432.26, 260.44, 543.44, 236.18, 610.14, 246.29, 737.49, 222.03, 860.79, 222.03, 998.25, 209.91, 1180.17, 167.46, 1319.65, 153.31, 1645.09, 155.33, 1816.91, 108.84, 2031.18, 106.82, 2164.59, 100.75, 2336.41, 133.09, 2421.31, 145.22, 2544.61, 153.31, 2629.51, 137.14, 2898.36, 110.86, 3054.0, 98.73, 3286.46, 185.65, 3474.45, 197.78, 3551.27, 171.5, 3646.27, 203.84, 3777.66, 262.46, 3848.41, 317.39, 3775.3, 314.0, 3763.79, 315.36, 3730.62, 322.13, 3675.79, 332.28, 3662.92, 344.21, 3660.55, 338.36, 3631.31, 339.53, 3598.55, 344.21, 3554.1, 340.7, 3516.67, 341.87, 3446.48, 351.23, 3290.9, 351.23, 3228.9, 353.57, 3224.22, 357.07, 3193.81, 355.9, 3161.05, 357.07, 3080.34, 367.6, 3011.32, 359.41, 2975.06, 368.77, 2963.36, 368.77, 2924.76, 368.77, 2860.42, 373.45, 2793.74, 379.3, 2702.5, 379.3, 2582.01, 382.81, 2580.84, 382.81, 2535.22, 388.66, 2459.18, 393.34, 2380.8, 393.34, 2284.88, 399.19, 2205.34, 398.02, 2145.68, 402.7, 2101.23, 405.04, 2068.47, 406.21, 2038.06, 405.04, 2005.3, 412.05, 1981.91, 412.05, 1940.97, 412.05, 1925.76, 409.71, 1871.95, 414.39, 1861.42, 414.39, 1845.04, 410.88, 1827.5, 415.56, 1788.89, 416.73, 1771.35, 417.9, 1751.46, 419.07, 1736.25, 417.9, 1721.05, 420.24, 1709.35, 420.96, 1691.62, 425.02, 1669.95, 420.29, 1658.45, 420.29, 1644.91, 425.02, 1636.78, 426.68, 1578.15, 428.66, 1513.57, 444.56, 1093.32, 460.45, 793.28, 459.55, 760.12, 459.55, 710.02, 462.93, 693.1, 460.9, 670.76, 465.16, 636.42, 466.57, 578.87]], "area": 802029.0, "bbox": [98.73, 357.47, 376.26, 3490.94], "iscrowd": 0, "attributes": {"wall frame": true, "window apron": false, "window header": false, "occluded": false}}]}